Workbook

Sheet SA P & L
A1: Profit and Loss | M1: Profit and Loss
A2: Saint Raphael PtyLtd t/a Sanctura | M2: Dr James Laporta Inc
A3: For the month ended 30 November 2025 | M3: For the month ended 30 November 2025
A5: Account | B5: Nov 2025 | C5: Oct 2025 | D5: Sep 2025 | E5: Aug 2025 | F5: Jul 2025 | G5: Jun 2025 | H5: May 2025 | I5: Apr 2025 | J5: Mar 2025 | K5: Year to date | M5: Account | N5: Nov 2025 | O5: Oct 2025 | P5: Sep 2025 | Q5: Aug 2025 | R5: Jul 2025 | S5: Jun 2025 | T5: May 2025 | U5: Apr 2025 | V5: Mar 2025 | W5: Year to date
A7: Trading Income | M7: Trading Income
A8: Interest Income | B8: 297.19 | C8: 225.96 | D8: 223.83 | E8: 325.99 | F8: 309.61 | G8: 233.47 | H8: 491.36 | I8: 606.07 | J8: 885.1 | K8: 3598.58 | M8: Interest Income | N8: 749.63 | O8: 2033.49 | P8: 249.61 | Q8: 1033.9 | R8: 1079.76 | S8: 2521.63 | T8: 2816.02 | U8: 2758.93 | V8: 3079.45 | W8: 16322.42
A9: Other Revenue | B9: 226590.89 | C9: 227857.39 | D9: 232162.92 | E9: 715957.99 | F9: 0 | G9: 0 | H9: 673482.97 | I9: 0 | J9: 0 | K9: 2076052.2 | M9: Sales | N9: 1092297.5 | O9: 1700808.7 | P9: 1506601.2 | Q9: 1457440.2 | R9: 1756178.4 | S9: 1600736.8 | T9: 2363910.7 | U9: 2257106.5 | V9: 2345295.3 | W9: 16080375
A10: Sales | B10: 1571884.9 | C10: 1830943.8 | D10: 1841449.7 | E10: 1842120.9 | F10: 1867679 | G10: 1590706.2 | H10: 1611732.3 | I10: 1878388.4 | J10: 1423966.8 | K10: 15458872 | M10: Total Trading Income | N10: =SUM(N8:N9) -> 1093047.1 | O10: =SUM(O8:O9) -> 1702842.2 | P10: =SUM(P8:P9) -> 1506850.9 | Q10: =SUM(Q8:Q9) -> 1458474.1 | R10: =SUM(R8:R9) -> 1757258.2 | S10: =SUM(S8:S9) -> 1603258.4 | T10: =SUM(T8:T9) -> 2366726.7 | U10: =SUM(U8:U9) -> 2259865.5 | ... W10: =SUM(W8:W9) -> 16096698
A11: Total Trading Income | B11: =SUM(B8:B10) -> 1798773 | C11: =SUM(C8:C10) -> 2059027.1 | D11: =SUM(D8:D10) -> 2073836.4 | E11: =SUM(E8:E10) -> 2558404.9 | F11: =SUM(F8:F10) -> 1867988.6 | G11: =SUM(G8:G10) -> 1590939.7 | H11: =SUM(H8:H10) -> 2285706.6 | I11: =SUM(I8:I10) -> 1878994.4 | ... K11: =SUM(K8:K10) -> 17538523
M12: Cost of Sales
A13: Cost of Sales | M13: Cost of Goods Sold | N13: 418076.09 | O13: 576951.25 | P13: 919714.77 | Q13: 1003861.2 | R13: 771216.25 | S13: 957081.16 | T13: 1337865.4 | U13: 876007.6 | V13: 150446.69 | W13: 7011220.4
A14: Cost of Goods Sold | B14: 138381.17 | C14: 145285.23 | D14: 118177.22 | E14: 110366.18 | F14: 155657.07 | G14: 138604.73 | H14: 191313.04 | I14: 291245.53 | J14: 556561.65 | K14: 1845591.8 | M14: Total Cost of Sales | N14: =N13 -> 418076.09 | O14: =O13 -> 576951.25 | P14: =P13 -> 919714.77 | Q14: =Q13 -> 1003861.2 | R14: =R13 -> 771216.25 | S14: =S13 -> 957081.16 | T14: =T13 -> 1337865.4 | U14: =U13 -> 876007.6 | ... W14: =W13 -> 7011220.4
A15: Total Cost of Sales | B15: =B14 -> 138381.17 | C15: =C14 -> 145285.23 | D15: =D14 -> 118177.22 | E15: =E14 -> 110366.18 | F15: =F14 -> 155657.07 | G15: =G14 -> 138604.73 | H15: =H14 -> 191313.04 | I15: =I14 -> 291245.53 | ... K15: =K14 -> 1845591.8
M16: Gross Profit | N16: =(N10 - N14) -> 674971.05 | O16: =(O10 - O14) -> 1125890.9 | P16: =(P10 - P14) -> 587136.09 | Q16: =(Q10 - Q14) -> 454612.93 | R16: =(R10 - R14) -> 986041.94 | S16: =(S10 - S14) -> 646177.28 | T16: =(T10 - T14) -> 1028861.3 | U16: =(U10 - U14) -> 1383857.9 | ... W16: =(W10 - W14) -> 9085477.5
A17: Gross Profit | B17: =(B11 - B15) -> 1660391.8 | C17: =(C11 - C15) -> 1913741.9 | D17: =(D11 - D15) -> 1955659.2 | E17: =(E11 - E15) -> 2448038.7 | F17: =(F11 - F15) -> 1712331.5 | G17: =(G11 - G15) -> 1452335 | H17: =(H11 - H15) -> 2094393.6 | I17: =(I11 - I15) -> 1587748.9 | ... K17: =(K11 - K15) -> 15692931
M18: Operating Expenses
A19: Operating Expenses | M19: Advertising | N19: 125000 | O19: 125000 | P19: 125000 | Q19: 125000 | R19: 125000 | S19: 125000 | T19: 125000 | U19: 125000 | V19: 125000 | W19: 1125000
A20: Advertising | B20: 53660.37 | C20: 98096.95 | D20: 76471.72 | E20: 85156.51 | F20: 79744.11 | G20: 76913.58 | H20: 124981.47 | I20: 61843.83 | J20: 96761 | K20: 753629.54 | M20: Bank Fees | N20: 24925.86 | O20: 17946.57 | P20: 23125.82 | Q20: 13750.99 | R20: 22209.27 | S20: 29420.87 | T20: 25394.76 | U20: 40612.19 | V20: 35453.59 | W20: 232839.92
A21: Bank Fees | B21: 1422.69 | C21: 773.79 | D21: 1688.74 | E21: 1705.1 | F21: 1801.35 | G21: 1958.28 | H21: 1407.04 | I21: 2097.87 | J21: 713.4 | K21: 13568.26 | M21: Cleaning & Office Expenses | N21: 18934.87 | O21: 25543.65 | P21: 23416.31 | Q21: 36128.42 | R21: 17464.25 | S21: 7346.11 | T21: 15429.66 | U21: 21968.14 | V21: 31499.63 | W21: 197731.04
A22: Casual Wages | B22: 0 | C22: 0 | D22: 0 | E22: 0 | F22: 2000 | G22: 0 | H22: 0 | I22: 18806.54 | J22: 24000 | K22: 44806.54 | M22: Consulting, Accounting & Administrative Fees | N22: 125000 | O22: 132438.32 | P22: 139348.09 | Q22: 165384.62 | R22: 0 | S22: 4400 | T22: 5400 | U22: 8100 | V22: 0 | W22: 580071.03
A23: Cleaning & Office Expenses | B23: 2550.22 | C23: 14706.18 | D23: 11153.76 | E23: 12754.31 | F23: 8488.79 | G23: 9645.7 | H23: 9122.58 | I23: 20457.15 | J23: 7152.99 | K23: 96031.68 | M23: Depreciation | N23: 26979.19 | O23: 27018.34 | P23: 26979.18 | Q23: 27018.33 | R23: 27018.29 | S23: 26979.22 | T23: 27018.32 | U23: 26979.18 | V23: 27018.32 | W23: 243008.37
A24: Consulting, Accounting & Administrative Fees | B24: 22945 | C24: 23950.39 | D24: 9542 | E24: 9542 | F24: 31669.5 | G24: 10571.25 | H24: 9542 | I24: 9542 | J24: 11094.5 | K24: 138398.64 | M24: Insurance | N24: 34962.81 | O24: 34962.81 | P24: 34962.81 | Q24: 51236.87 | R24: 18688.75 | S24: 18682.66 | T24: 18682.66 | U24: 18682.66 | V24: 18682.66 | W24: 249544.69
A25: Depreciation | B25: 277684.38 | C25: 277684.36 | D25: 277684.32 | E25: 277684.31 | F25: 277746.87 | G25: 277749.47 | H25: 277749.47 | I25: 277749.52 | J25: 277749.45 | K25: 2499482.1 | M25: MGNT - Accounting and other related services | N25: 29636.09 | O25: 0 | P25: 19735.84 | Q25: 0 | R25: 0 | S25: 23050.61 | T25: 34040.31 | U25: 32502.33 | V25: 33772.25 | W25: 172737.43
A26: Donations | B26: 0 | C26: 0 | D26: 0 | E26: 0 | F26: 0 | G26: 7000 | H26: 0 | I26: 0 | J26: 0 | K26: 7000 | M26: MGNT - Equipment rental | N26: 10000 | O26: 0 | P26: 10000 | Q26: 0 | R26: 0 | S26: 30000 | T26: 30000 | U26: 30000 | V26: 30000 | W26: 140000
A27: Legal expenses | B27: 0 | C27: 0 | D27: 0 | E27: 0 | F27: 0 | G27: 0 | H27: 0 | I27: 4561.88 | J27: 2108.34 | K27: 6670.22 | M27: MGNT - Patients / Surgery management | N27: 29636.09 | O27: 0 | P27: 40445.36 | Q27: 0 | R27: 0 | S27: 72033.16 | T27: 106375.98 | U27: 101569.79 | V27: 105538.29 | W27: 455598.67
A28: Medical Waste | B28: 0 | C28: 1122.52 | D28: 10182.12 | E28: 7514.72 | F28: 812.49 | G28: 633.66 | H28: 807.32 | I28: 6566.54 | J28: 1980.9 | K28: 29620.27 | M28: MGNT - Practice Management | N28: 29636.09 | O28: 0 | P28: 67030.91 | Q28: 0 | R28: 0 | S28: 108049.73 | T28: 159563.97 | U28: 152354.69 | V28: 158307.43 | W28: 674942.82
A29: Minor Assets | B29: 3477.39 | C29: 0 | D29: 0 | E29: 0 | F29: 0 | G29: 0 | H29: 0 | I29: 0 | J29: 10004 | K29: 13481.39 | M29: MGNT - Rental | N29: 29636.09 | O29: 0 | P29: 21373.81 | Q29: 0 | R29: 0 | S29: 36016.58 | T29: 53187.99 | U29: 50784.9 | V29: 52769.14 | W29: 243768.51
A30: Motor Vehicle Expenses & Fuel | B30: 0 | C30: 1150 | D30: 0 | E30: 0 | F30: 0 | G30: 0 | H30: 0 | I30: 0 | J30: 0 | K30: 1150 | M30: Minor Assets | N30: 5925 | O30: 10777.58 | P30: 0 | Q30: 0 | R30: 0 | S30: 0 | T30: 0 | U30: 11755.08 | V30: 6486.95 | W30: 34944.61
A31: Payroll : Director Nett | B31: 31983.55 | C31: 31983.55 | D31: 31983.55 | E31: 31983.55 | F31: 31983.54 | G31: 31983.55 | H31: 31983.55 | I31: 31983.54 | J31: 31983.55 | K31: 287851.93 | M31: Motor Vehicle Expense - Fuel | N31: 2547.92 | O31: 7839.21 | P31: 9886.4 | Q31: 3224.24 | R31: 9912.61 | S31: 4707.2 | T31: 6822.75 | U31: 6272.3 | V31: 11317.99 | W31: 62530.62
... A47: Utilities | B47: 1739.13 | C47: 13043.49 | D47: 5000 | E47: 5000 | F47: 4000 | G47: 2100 | H47: 0 | I47: 0 | J47: 0 | K47: 30882.62 | M47: TOT - Data capture | N47: 0 | O47: 0 | P47: 18079.22 | Q47: 17489.28 | R47: 21074.14 | S47: 19208.84 | T47: 28366.93 | U47: 27085.28 | V47: 28143.54 | W47: 159447.23
A48: Total Operating Expenses | B48: =SUM(B20:B47) -> 1264229.6 | C48: =SUM(C20:C47) -> 1445047.7 | D48: =SUM(D20:D47) -> 1457359.9 | E48: =SUM(E20:E47) -> 1445114.6 | F48: =SUM(F20:F47) -> 1615150.2 | G48: =SUM(G20:G47) -> 1447641.3 | H48: =SUM(H20:H47) -> 1423132.5 | I48: =SUM(I20:I47) -> 1364574.2 | ... K48: =SUM(K20:K47) -> 12798932 | M48: TOT - Medical patients records | N48: 0 | O48: 0 | P48: 12052.81 | Q48: 11659.52 | R48: 14049.43 | S48: 12805.89 | T48: 18911.29 | U48: 18056.85 | V48: 18762.36 | W48: 106298.15
M49: Travel - International | N49: 206514.51 | O49: 145637.63 | P49: 157986.56 | Q49: 153591.64 | R49: 121106.47 | S49: 135958.68 | T49: 66424.61 | U49: 42561.52 | V49: 0 | W49: 1029781.6
A50: Net Profit | B50: =((B17 + 0) - B48) -> 396162.2 | C50: =((C17 + 0) - C48) -> 468694.21 | D50: =((D17 + 0) - D48) -> 498299.32 | E50: =((E17 + 0) - E48) -> 1002924.1 | F50: =((F17 + 0) - F48) -> 97181.28 | G50: =((G17 + 0) - G48) -> 4693.72 | H50: =((H17 + 0) - H48) -> 671261.04 | I50: =((I17 + 0) - I48) -> 223174.74 | ... K50: =((K17 + 0) - K48) -> 2893998.6 | M50: Travel - National | N50: 13580.02 | O50: 54920.9 | P50: 33644.18 | Q50: 7949.6 | R50: 6940.06 | S50: 5126.13 | T50: 7506.09 | U50: 6635.69 | V50: 1545.22 | W50: 137847.89
M51: Utilities | N51: 4347.83 | O51: 0 | P51: 4347.83 | Q51: 0 | R51: 5217.39 | S51: 0 | T51: 0 | U51: 0 | V51: 0 | W51: 13913.05
M52: Total Operating Expenses | N52: =SUM(N19:N51) -> 1956108.5 | O52: =SUM(O19:O51) -> 2045880.4 | P52: =SUM(P19:P51) -> 2141548.1 | Q52: =SUM(Q19:Q51) -> 1942706.8 | R52: =SUM(R19:R51) -> 1880238.8 | S52: =SUM(S19:S51) -> 2029121.2 | T52: =SUM(T19:T51) -> 2026302 | U52: =SUM(U19:U51) -> 2081013.1 | ... W52: =SUM(W19:W51) -> 18114019
M54: Net Profit | N54: =((N16 + 0) - N52) -> -1281137.5 | O54: =((O16 + 0) - O52) -> -919989.47 | P54: =((P16 + 0) - P52) -> -1554412 | Q54: =((Q16 + 0) - Q52) -> -1488093.9 | R54: =((R16 + 0) - R52) -> -894196.82 | S54: =((S16 + 0) - S52) -> -1382943.9 | T54: =((T16 + 0) - T52) -> -997440.71 | U54: =((U16 + 0) - U52) -> -697155.19 | ... W54: =((W16 + 0) - W52) -> -9028541.6
Q56: =W52+K48-1125000 -> 29787951

Sheet Combined
A1: Profit and Loss Combined | E1: Within 25% of Budget | H1: Over 25% of Budget | K1: Under 25% of Budget
A2: Sanctura SA
A3: For the month ended 30 November 2025
B4: Saint Raphael | C4: JLI | D4: Intracompany | E4: Total Comb | F4: Reforecast | G4: % Variance | H4: R Variance | J4: Year to Date | K4: Reforecast YTD | L4: % Variance | M4: R Variance
A5: Account | B5: 45962 | C5: 45962 | D5: 45962 | E5: 45962 | F5: 45962 | G5: 45962 | H5: 45962 | J5: 45962 | K5: 45962 | L5: 45962 | M5: 45962
A7: Trading Income
A8: Interest Income | B8: ='SA P & L'!B8 -> 297.19 | C8: ='SA P & L'!N8 -> 749.63 | E8: =SUM(B8:D8) -> 1046.82 | J8: ='SA P & L'!W8+'SA P & L'!K8 -> 19921
A9: Sales | B9: ='SA P & L'!B10 -> 1571884.9 | C9: ='SA P & L'!N9 -> 1092297.5 | D9: =-1571885 -> -1571885 | E9: =SUM(B9:D9) -> 1092297.4 | F9: ='SA V2'!S273 -> 2397090.4 | J9: ='SA P & L'!W9 -> 16080375 | K9: =SUM('SA V2'!K273:S273) -> 19245201
A10: Total Trading Income | B10: =SUM(B8:B9) -> 1572182.1 | C10: =SUM(C8:C9) -> 1093047.1 | D10: =SUM(D8:D9) -> -1571885 | E10: =SUM(E8:E9) -> 1093344.2 | F10: =SUM(F8:F9) -> 2397090.4 | G10: =(E10-F10)/F10*100 -> -54.388694 | H10: =E10-F10 -> -1303746.1 | J10: =SUM(J8:J9) -> 16100296 | K10: =SUM(K9:K9) -> 19245201 | L10: =(J10-K10)/K10*100 -> -16.34124 | M10: =J10-K10 -> -3144904.5
A12: Cost of Sales
A13: Cost of Goods Sold | B13: ='SA P & L'!B14 -> 138381.17 | C13: ='SA P & L'!N13 -> 418076.09 | D13: =-231635 -> -231635 | E13: =SUM(B13:D13) -> 324822.26 | F13: =-SUM('SA V2'!S276:S287) -> 796080.52 | J13: ='SA P & L'!K14+'SA P & L'!W13-N13 -> 5898711 | K13: =-SUM('SA V2'!K276:S287) -> 6923922.3 | N13: =2447398.19+279069+231634 -> 2958101.2
A14: Total Cost of Sales | B14: =B13 -> 138381.17 | C14: =C13 -> 418076.09 | D14: =D13 -> -231635 | E14: =E13 -> 324822.26 | F14: =F13 -> 796080.52 | G14: =(E14-F14)/F14*100 -> -59.197311 | H14: =E14-F14 -> -471258.26 | J14: =J13 -> 5898711 | K14: =K13 -> 6923922.3 | L14: =(J14-K14)/K14*100 -> -14.8068 | M14: =J14-K14 -> -1025211.3
A16: Gross Profit | B16: =(B10 - B14) -> 1433800.9 | C16: =(C10 - C14) -> 674971.05 | E16: =(E10 - E14) -> 768521.97 | F16: =(F10 - F14) -> 1601009.9 | G16: =(E16-F16)/F16*100 -> -51.997674 | H16: =E16-F16 -> -832487.89 | J16: =(J10 - J14) -> 10201585 | K16: =(K10 - K14) -> 12321279 | L16: =(J16-K16)/K16*100 -> -17.203517 | M16: =J16-K16 -> -2119693.2
A18: Operating Expenses
A19: Bank Fees | B19: ='SA P & L'!B21 -> 1422.69 | C19: ='SA P & L'!N20 -> 24925.86 | E19: =SUM(B19:D19) -> 26348.55 | F19: ='SA V2'!S205 -> 28980.143 | G19: =(E19-F19)/F19*100 -> -9.0806759 | H19: =E19-F19 -> -2631.5929 | J19: ='SA P & L'!K21+'SA P & L'!W20 -> 246408.18 | K19: =SUM('SA V2'!K205:S205) -> 270978.57 | L19: =(J19-K19)/K19*100 -> -9.0672821 | M19: =J19-K19 -> -24570.391
A20: Casual Wages | B20: ='SA P & L'!B22 -> 0 | C20: 0 | E20: =SUM(B20:D20) -> 0 | F20: ='SA V2'!S206 -> 5600 | G20: =(E20-F20)/F20*100 -> -100 | H20: =E20-F20 -> -5600 | J20: ='SA P & L'!K22 -> 44806.54 | K20: =SUM('SA V2'!K206:S206) -> 24400 | L20: =(J20-K20)/K20*100 -> 83.633361 | M20: =J20-K20 -> 20406.54
A21: Consulting, Accounting, Legal & Administrative Fees | B21: ='SA P & L'!B24 -> 22945 | C21: ='SA P & L'!N22-125000 -> 0 | E21: =SUM(B21:D21) -> 22945 | F21: ='SA V2'!S207 -> 24076.857 | G21: =(E21-F21)/F21*100 -> -4.701017 | H21: =E21-F21 -> -1131.8571 | J21: ='SA P & L'!K24+'SA P & L'!K27+'SA P & L'!W22-N43 -> 184755.27 | K21: =SUM('SA V2'!K207:S207) -> 200297.43 | L21: =(J21-K21)/K21*100 -> -7.7595397 | M21: =J21-K21 -> -15542.159
A22: Entertainment & Staff Welfare | B22: ='SA P & L'!B42 -> 15450 | C22: ='SA P & L'!N43 -> 6035.09 | E22: =SUM(B22:D22) -> 21485.09 | F22: ='SA V2'!S209 -> 13439.857 | G22: =(E22-F22)/F22*100 -> 59.861 | H22: =E22-F22 -> 8045.2329 | J22: ='SA P & L'!K42+'SA P & L'!W43 -> 115197.32 | K22: =SUM('SA V2'!K209:S209) -> 110181.43 | L22: =(J22-K22)/K22*100 -> 4.5523928 | M22: =J22-K22 -> 5015.8914
A23: Freight & Courier, Printing & Stationary | B23: ='SA P & L'!B37+'SA P & L'!B36 -> 3800.9 | C23: ='SA P & L'!N36+'SA P & L'!N37 -> 3639.31 | E23: =SUM(B23:D23) -> 7440.21 | F23: ='SA V2'!S210 -> 9210.4286 | G23: =(E23-F23)/F23*100 -> -19.21972 | H23: =E23-F23 -> -1770.2186 | J23: ='SA P & L'!K36+'SA P & L'!K37+'SA P & L'!W36+'SA P & L'!W37 -> 78596.19 | K23: =SUM('SA V2'!K210:S210) -> 93895.714 | L23: =(J23-K23)/K23*100 -> -16.294167 | M23: =J23-K23 -> -15299.524
A24: Insurance | B24: =0 -> 0 | C24: ='SA P & L'!N24 -> 34962.81 | E24: =SUM(B24:D24) -> 34962.81 | F24: ='SA V2'!S211 -> 60480 | G24: =(E24-F24)/F24*100 -> -42.191121 | H24: =E24-F24 -> -25517.19 | J24: ='SA P & L'!W24 -> 249544.69 | K24: =SUM('SA V2'!K211:S211) -> 362132 | L24: =(J24-K24)/K24*100 -> -31.09013 | M24: =J24-K24 -> -112587.31
A25: Minor assets | B25: ='SA P & L'!B29 -> 3477.39 | C25: ='SA P & L'!N30 -> 5925 | E25: =SUM(B25:D25) -> 9402.39 | F25: ='SA V2'!S212 -> 6975 | G25: =(E25-F25)/F25*100 -> 34.80129 | H25: =E25-F25 -> 2427.39 | J25: ='SA P & L'!W30+'SA P & L'!K29 -> 48426 | K25: =SUM('SA V2'!K212:S212) -> 57874 | L25: =(J25-K25)/K25*100 -> -16.32512 | M25: =J25-K25 -> -9448
A26: Motor Vehicle Expenses and Fuel | B26: 0 | C26: ='SA P & L'!N31+'SA P & L'!N32 -> 3234 | E26: =SUM(B26:D26) -> 3234 | F26: ='SA V2'!S213 -> 25845.571 | G26: =(E26-F26)/F26*100 -> -87.487218 | H26: =E26-F26 -> -22611.571 | J26: ='SA P & L'!W31+'SA P & L'!W32+'SA P & L'!K30 -> 116186.89 | K26: =SUM('SA V2'!K213:S213) -> 190107.29 | L26: =(J26-K26)/K26*100 -> -38.883515 | M26: =J26-K26 -> -73920.396
A27: Office, Cleaning, Medical Waste, Security | B27: ='SA P & L'!B23+'SA P & L'!B26+'SA P & L'!B28 -> 2550.22 | C27: ='SA P & L'!N40+'SA P & L'!N21 -> 19448.95 | E27: =SUM(B27:D27) -> 21999.17 | F27: ='SA V2'!S214 -> 28257.286 | G27: =(E27-F27)/F27*100 -> -22.14691 | H27: =E27-F27 -> -6258.1157 | J27: ='SA P & L'!W21+'SA P & L'!W40+'SA P & L'!K28+'SA P & L'!K23+'SA P & L'!K26 -> 334696.66 | K27: =SUM('SA V2'!K214:S214) -> 260677.14 | L27: =(J27-K27)/K27*100 -> 28.395093 | M27: =J27-K27 -> 74019.517
A28: Rent and Utilities | B28: ='SA P & L'!B39+'SA P & L'!B47 -> 81413.16 | C28: ='SA P & L'!N51 -> 4347.83 | E28: =SUM(B28:D28) -> 85760.99 | F28: ='SA V2'!S215 -> 98609.143 | G28: =(E28-F28)/F28*100 -> -13.029373 | H28: =E28-F28 -> -12848.153 | J28: ='SA P & L'!W51+'SA P & L'!K47+'SA P & L'!K39 -> 859727.07 | K28: =SUM('SA V2'!K215:S215) -> 885734.57 | L28: =(J28-K28)/K28*100 -> -2.9362636 | M28: =J28-K28 -> -26007.501
A29: Repairs and Maintenance | B29: ='SA P & L'!B40 -> 21556.05 | C29: ='SA P & L'!N38 -> 485.22 | E29: =SUM(B29:D29) -> 22041.27 | F29: ='SA V2'!S216 -> 5674.7143 | G29: =(E29-F29)/F29*100 -> 288.41198 | H29: =E29-F29 -> 16366.556 | J29: ='SA P & L'!K40+'SA P & L'!W38 -> 250318.15 | K29: =SUM('SA V2'!K216:S216) -> 43802.857 | L29: =(J29-K29)/K29*100 -> 471.46535 | M29: =J29-K29 -> 206515.29
A30: Staff Clothing | B30: =0 -> 0 | C30: ='SA P & L'!N41 -> 0 | E30: =SUM(B30:D30) -> 0 | F30: ='SA V2'!S217 -> 2120.2857 | G30: =(E30-F30)/F30*100 -> -100 | H30: =E30-F30 -> -2120.2857 | J30: ='SA P & L'!W41 -> 25682.6 | K30: =SUM('SA V2'!K217:S217) -> 22829.143 | L30: =(J30-K30)/K30*100 -> 12.499187 | M30: =J30-K30 -> 2853.4571
A31: Subscriptions | B31: ='SA P & L'!B43 -> 30262.2 | C31: ='SA P & L'!N44 -> 3594.09 | E31: =SUM(B31:D31) -> 33856.29 | F31: ='SA V2'!S218 -> 22047.714 | G31: =(E31-F31)/F31*100 -> 53.559183 | H31: =E31-F31 -> 11808.576 | J31: ='SA P & L'!W44+'SA P & L'!K43 -> 261540.75 | K31: =SUM('SA V2'!K218:S218) -> 211792.86 | L31: =(J31-K31)/K31*100 -> 23.488938 | M31: =J31-K31 -> 49747.893
A32: Telephone & Internet | B32: =0 -> 0 | C32: ='SA P & L'!N45 -> 8642.3 | E32: =SUM(B32:D32) -> 8642.3 | F32: ='SA V2'!S219 -> 5219.8571 | G32: =(E32-F32)/F32*100 -> 65.565834 | H32: =E32-F32 -> 3422.4429 | J32: ='SA P & L'!W45 -> 52826.5 | K32: =SUM('SA V2'!K219:S219) -> 46734.429 | L32: =(J32-K32)/K32*100 -> 13.035511 | M32: =J32-K32 -> 6092.0714
A33: Training and conferences | B33: ='SA P & L'!B41 -> -20052.18 | C33: ='SA P & L'!N42 -> 0 | E33: =SUM(B33:D33) -> -20052.18 | F33: ='SA V2'!S220 -> 10624.286 | G33: =(E33-F33)/F33*100 -> -288.73909 | H33: =E33-F33 -> -30676.466 | J33: ='SA P & L'!K41+'SA P & L'!W42 -> 75312.82 | K33: =SUM('SA V2'!K220:S220) -> 105519.14 | L33: =(J33-K33)/K33*100 -> -28.626391 | M33: =J33-K33 -> -30206.323
A34: Travel - International | B34: ='SA P & L'!B44 -> 72397.39 | C34: ='SA P & L'!N49 -> 206514.51 | E34: =SUM(B34:D34) -> 278911.9 | F34: ='SA V2'!S221 -> 161387 | G34: =(E34-F34)/F34*100 -> 72.821789 | H34: =E34-F34 -> 117524.9 | J34: ='SA P & L'!K44+'SA P & L'!W49 -> 1923653.5 | K34: =SUM('SA V2'!K221:S221) -> 1691737 | L34: =(J34-K34)/K34*100 -> 13.708782 | M34: =J34-K34 -> 231916.54
A35: Travel - National | B35: ='SA P & L'!B45 -> 0 | C35: ='SA P & L'!N50 -> 13580.02 | E35: =SUM(B35:D35) -> 13580.02 | F35: ='SA V2'!S222 -> 5347.1429 | G35: =(E35-F35)/F35*100 -> 153.96778 | H35: =E35-F35 -> 8232.8771 | J35: ='SA P & L'!W50+'SA P & L'!K45 -> 146911.31 | K35: =SUM('SA V2'!K222:S222) -> 49378.571 | L35: =(J35-K35)/K35*100 -> 197.52037 | M35: =J35-K35 -> 97532.739
A36: Contingency | B36: 0 | C36: 0 | E36: =SUM(B36:D36) -> 0 | F36: ='SA V2'!S223 -> 35000 | G36: =(E36-F36)/F36*100 -> -100 | H36: =E36-F36 -> -35000 | J36: 0 | K36: =SUM('SA V2'!K223:S223) -> 315000 | L36: =(J36-K36)/K36*100 -> -100 | M36: =J36-K36 -> -315000
A37: Advertising | B37: ='SA P & L'!B20 -> 53660.37 | C37: ='SA P & L'!N19 -> 125000 | D37: =-125000 -> -125000 | E37: =SUM(B37:D37) -> 53660.37 | F37: ='SA V2'!S204 -> 125000 | G37: =(E37-F37)/F37*100 -> -57.071704 | H37: =E37-F37 -> -71339.63 | J37: ='SA P & L'!K20 -> 753629.54 | K37: =SUM('SA V2'!K204:S204) -> 940243 | L37: =(J37-K37)/K37*100 -> -19.847365 | M37: =J37-K37 -> -186613.46
A38: Practice Management | B38: 0 | C38: ='SA P & L'!N39 -> 1215250 | D38: =-1215250 -> -1215250 | E38: =SUM(B38:D38) -> 0 | H38: =E38-F38 -> 0
A39: Unrealised Currency Gains / Losses | B39: ='SA P & L'!B38+'SA P & L'!B46 -> 8790.78 | E39: =SUM(B39:D39) -> 8790.78 | J39: ='SA P & L'!K38+'SA P & L'!K46 -> -13774.97
E40: =SUM(B40:D40) -> 0
A41: Staff Costs: | E41: =SUM(B41:D41) -> 0
A42: Director's Emoluments | B42: ='SA P & L'!B31+'SA P & L'!B32 -> 40000 | C42: =SUM('SA P & L'!N46:N48)+SUM('SA P & L'!N25:N29) -> 128544.36 | E42: =SUM(B42:D42) -> 168544.36 | F42: ='SA V2'!S181 -> 250000 | G42: =(E42-F42)/F42*100 -> -32.582256 | H42: =E42-F42 -> -81455.64 | J42: ='SA P & L'!K31+'SA P & L'!K32+SUM('SA P & L'!W46:W48)+SUM('SA P & L'!W25:W29) -> 2379229.1 | K42: =-(SUM('SA V2'!K296:R296)) -> 2000000 | L42: =(J42-K42)/K42*100 -> 18.961457 | M42: =J42-K42 -> 379229.15
A43: Wages and Salaries | B43: ='SA P & L'!B33+'SA P & L'!B34+'SA P & L'!B35 -> 648871.26 | C43: 125000 | E43: =SUM(B43:D43) -> 773871.26 | F43: =-('SA V2'!S298-'SA V2'!S296) -> 890746.39 | G43: =(E43-F43)/F43*100 -> -13.121033 | H43: =E43-F43 -> -116875.13 | J43: =SUM('SA P & L'!K33:K35)+SUM('SA P & L'!W33:W35)+N43 -> 7536016.5 | K43: =(-SUM('SA V2'!K298:S298)-Combined!K42) -> 7935628.9 | L43: =(J43-K43)/K43*100 -> -5.0356747 | M43: =J43-K43 -> -399612.46 | N43: =290384.62+125000+125000 -> 540384.62
E44: =SUM(B44:D44) -> 0
A45: No Cash Movement: | E45: =SUM(B45:D45) -> 0
A46: Depreciation | B46: ='SA P & L'!B25 -> 277684.38 | C46: ='SA P & L'!N23 -> 26979.19 | E46: =SUM(B46:D46) -> 304663.57 | F46: ='SA V2'!S208 -> 305633 | G46: =(E46-F46)/F46*100 -> -0.31718761 | H46: =E46-F46 -> -969.43 | J46: ='SA P & L'!K25+'SA P & L'!W23 -> 2742490.5 | K46: =SUM('SA V2'!K208:S208) -> 2750697 | L46: =(J46-K46)/K46*100 -> -0.29834184 | M46: =J46-K46 -> -8206.48
A47: Interest Expense | E47: =SUM(B47:D47) -> 0 | H47: =E47-F47 -> 0
A48: Total Operating Expenses | B48: =SUM(B19:B47) -> 1264229.6 | C48: =SUM(C19:C47) -> 1956108.5 | D48: =D13+D37+D38 -> -1571885 | E48: =SUM(E19:E47) -> 1880088.2 | F48: =SUM(F19:F47) -> 2120274.7 | G48: =(E48-F48)/F48*100 -> -11.328085 | H48: =SUM(H19:H47) -> -248977.3 | J48: =SUM(J19:J47) -> 18412181 | K48: =SUM(K19:K47) -> 18569641 | L48: =(J48-K48)/K48*100 -> -0.84794252 | M48: =SUM(M19:M47) -> -143684.91
A50: Net Profit | B50: =B16-B48 -> 169571.31 | C50: =C16-C48 -> -1281137.5 | E50: =E16-E48 -> -1111566.2 | F50: =((F16 + 0) - F48) -> -519264.81 | G50: =(E50-F50)/F50*100 -> 114.06538 | H50: =E50-F50 -> -592301.37 | J50: =J16-J48 -> -8210595.8 | K50: =((K16 + 0) - K48) -> -6248362.5 | L50: =(J50-K50)/K50*100 -> 31.403961 | M50: =J50-K50 -> -1962233.3

Sheet SA V2
C1: GBP | D1: =D3/$D$2 -> -359792.81 | E1: =E3/$D$2 -> 170927.79 | F1: =F3/$D$2 -> 345477.59 | G1: =G3/$D$2 -> 937456.63
C2: GBP:ZAR | D2: =22.6-(22.6*0.4%) -> 22.5096 | I2: =YEAR(I4) -> 2025 | J2: =YEAR(J4) -> 2025 | K2: =YEAR(K4) -> 2025 | L2: =YEAR(L4) -> 2025 | M2: =YEAR(M4) -> 2025 | N2: =YEAR(N4) -> 2025 | O2: =YEAR(O4) -> 2025 | P2: =YEAR(P4) -> 2025 | ... BD2: =YEAR(BD4) -> 2028
C3: Rands | D3: =D$354 -> -8098792.2 | E3: =E$354 -> 3847516.1 | F3: =F$354 -> 7776562.4 | G3: =G$354 -> 21101774 | I3: Actual | J3: Actual | K3: Actual | L3: Actual | M3: Actual | N3: Actual | O3: Actual | P3: Forecast
D4: 2025 | E4: 2026 | F4: 2027 | G4: 2028 | I4: 45688 | J4: =EOMONTH(I4,1) -> 45716 | K4: =EOMONTH(J4,1) -> 45747 | L4: =EOMONTH(K4,1) -> 45777 | M4: =EOMONTH(L4,1) -> 45808 | N4: =EOMONTH(M4,1) -> 45838 | O4: =EOMONTH(N4,1) -> 45869 | P4: =EOMONTH(O4,1) -> 45900 | Q4: =EOMONTH(P4,1) -> 45930 | ... BD4: =EOMONTH(BC4,1) -> 47118
B5: ASSUMPTIONS
B7: Revenue Assumptions
C9: Treatment commencement | D9: =I4 -> 45688 | I9: =IF(I4>=$D$9,1,0) -> 1 | J9: =IF(J4>=$D$9,1,0) -> 1 | K9: =IF(K4>=$D$9,1,0) -> 1 | L9: =IF(L4>=$D$9,1,0) -> 1 | M9: =IF(M4>=$D$9,1,0) -> 1 | N9: =IF(N4>=$D$9,1,0) -> 1 | O9: =IF(O4>=$D$9,1,0) -> 1 | P9: =IF(P4>=$D$9,1,0) -> 1 | ... BD9: =IF(BD4>=$D$9,1,0) -> 1
C12: IV Treatments | D12: Min | E12: Max | F12: Growth Rate
C13: IV Number of Treatments | D13: 25 | E13: 200 | F13: 0.01 | I13: 47 | J13: 43 | K13: 63 | L13: 54 | M13: 39 | N13: 35 | O13: 75 | P13: =MIN(MAX($D13,O13)*(1+$F13)*P$9,$E13) -> 75.75 | Q13: =MIN(MAX($D13,P13)*(1+$F13)*Q$9,$E13) -> 76.5075 | R13: =MIN(MAX($D13,Q13)*(1+$F13)*R$9,$E13) -> 77.272575 | S13: =MIN(MAX($D13,R13)*(1+$F13)*S$9,$E13) -> 78.045301 | T13: =MIN(MAX($D13,S13)*(1+$F13)*T$9,$E13) -> 78.825754 | U13: =MIN(MAX($D13,T13)*(1+$F13)*U$9,$E13) -> 79.614011 | V13: =MIN(MAX($D13,U13)*(1+$F13)*V$9,$E13) -> 80.410151 | W13: =MIN(MAX($D13,V13)*(1+$F13)*W$9,$E13) -> 81.214253 | ... BD13: =MIN(MAX($D13,BC13)*(1+$F13)*BD$9,$E13) -> 112.78143
C14: Average Revenue / Treatment | D14: 3500 | E14: 4500 | F14: 0 | I14: 3320 | J14: 4101 | K14: 3165 | L14: 4502 | M14: 4166 | N14: 3777 | O14: 3143 | P14: =MIN(MAX($D14,O14)*(1+$F14)*P$9,$E14) -> 3500 | Q14: =MIN(MAX($D14,P14)*(1+$F14)*Q$9,$E14) -> 3500 | R14: =MIN(MAX($D14,Q14)*(1+$F14)*R$9,$E14) -> 3500 | S14: =MIN(MAX($D14,R14)*(1+$F14)*S$9,$E14) -> 3500 | T14: =MIN(MAX($D14,S14)*(1+$F14)*T$9,$E14) -> 3500 | U14: =MIN(MAX($D14,T14)*(1+$F14)*U$9,$E14) -> 3500 | V14: =MIN(MAX($D14,U14)*(1+$F14)*V$9,$E14) -> 3500 | W14: =MIN(MAX($D14,V14)*(1+$F14)*W$9,$E14) -> 3500 | ... BD14: =MIN(MAX($D14,BC14)*(1+$F14)*BD$9,$E14) -> 3500
C15: IV Treatment Revenue | I15: =I13*I14 -> 156040 | J15: =J13*J14 -> 176343 | K15: =K13*K14 -> 199395 | L15: =L13*L14 -> 243108 | M15: =M13*M14 -> 162474 | N15: =N13*N14 -> 132195 | O15: =O13*O14 -> 235725 | P15: =P13*P14 -> 265125 | ... BD15: =BD13*BD14 -> 394735
C17: IV COS | D17: =-(D14*0.3) -> -1050 | I17: =-I15*0.3 -> -46812 | J17: =-J15*0.3 -> -52902.9 | K17: =-K15*0.3 -> -59818.5 | L17: =-L15*0.3 -> -72932.4 | M17: =-M15*0.3 -> -48742.2 | N17: =-N15*0.3 -> -39658.5 | O17: =-O15*0.3 -> -70717.5 | P17: =P13*$D17 -> -79537.5 | Q17: =Q13*$D17 -> -80332.875 | R17: =R13*$D17 -> -81136.204 | S17: =S13*$D17 -> -81947.566 | T17: =T13*$D17 -> -82767.041 | U17: =U13*$D17 -> -83594.712 | V17: =V13*$D17 -> -84430.659 | W17: =W13*$D17 -> -85274.966 | ... BD17: =BD13*$D17 -> -118420.5
C19: IV Curcumin 150mg Treatments | D19: Min | E19: Max | F19: Growth Rate
C20: IV Curcumin Number of Treatments | D20: 25 | E20: 45 | F20: 0.01 | I20: 29 | J20: =MIN(MAX($D20,I20)*(1+$F20)*J$9,$E20) -> 29.29 | K20: 32 | L20: 39 | M20: 15 | N20: 7 | O20: 28 | P20: =MIN(MAX($D20,O20)*(1+$F20)*P$9,$E20) -> 28.28 | Q20: =MIN(MAX($D20,P20)*(1+$F20)*Q$9,$E20) -> 28.5628 | R20: =MIN(MAX($D20,Q20)*(1+$F20)*R$9,$E20) -> 28.848428 | S20: =MIN(MAX($D20,R20)*(1+$F20)*S$9,$E20) -> 29.136912 | T20: =MIN(MAX($D20,S20)*(1+$F20)*T$9,$E20) -> 29.428281 | U20: =MIN(MAX($D20,T20)*(1+$F20)*U$9,$E20) -> 29.722564 | V20: =MIN(MAX($D20,U20)*(1+$F20)*V$9,$E20) -> 30.01979 | W20: =MIN(MAX($D20,V20)*(1+$F20)*W$9,$E20) -> 30.319988 | ... BD20: =MIN(MAX($D20,BC20)*(1+$F20)*BD$9,$E20) -> 42.105066
C21: Average Revenue / Treatment | D21: 6500 | E21: 7500 | F21: 0.02 | I21: 5016 | J21: 5379 | K21: 5898 | L21: 6045 | M21: 5762 | N21: 7000 | O21: 5026 | P21: =MIN(MAX($D21,O21)*(1+$F21)*P$9,$E21) -> 6630 | Q21: =MIN(MAX($D21,P21)*(1+$F21)*Q$9,$E21) -> 6762.6 | R21: =MIN(MAX($D21,Q21)*(1+$F21)*R$9,$E21) -> 6897.852 | S21: =MIN(MAX($D21,R21)*(1+$F21)*S$9,$E21) -> 7035.809 | T21: =MIN(MAX($D21,S21)*(1+$F21)*T$9,$E21) -> 7176.5252 | U21: =MIN(MAX($D21,T21)*(1+$F21)*U$9,$E21) -> 7320.0557 | V21: =MIN(MAX($D21,U21)*(1+$F21)*V$9,$E21) -> 7466.4568 | W21: =MIN(MAX($D21,V21)*(1+$F21)*W$9,$E21) -> 7500 | ... BD21: =MIN(MAX($D21,BC21)*(1+$F21)*BD$9,$E21) -> 7500
C22: IV CurcuminTreatment Revenue | I22: =I20*I21 -> 145464 | J22: =J20*J21 -> 157550.91 | K22: =K20*K21 -> 188736 | L22: =L20*L21 -> 235755 | M22: =M20*M21 -> 86430 | N22: =N20*N21 -> 49000 | O22: =O20*O21 -> 140728 | P22: =P20*P21 -> 187496.4 | ... BD22: =BD20*BD21 -> 315788
C24: IV Curcumin COS | D24: =-(D21*0.3) -> -1950 | I24: =-I22*0.3 -> -43639.2 | J24: =-J22*0.3 -> -47265.273 | K24: =-K22*0.3 -> -56620.8 | L24: =-L22*0.3 -> -70726.5 | M24: =-M22*0.3 -> -25929 | N24: =-N22*0.3 -> -14700 | O24: =-O22*0.3 -> -42218.4 | P24: =P20*$D24 -> -55146 | Q24: =Q20*$D24 -> -55697.46 | R24: =R20*$D24 -> -56254.435 | S24: =S20*$D24 -> -56816.979 | T24: =T20*$D24 -> -57385.149 | U24: =U20*$D24 -> -57959 | V24: =V20*$D24 -> -58538.59 | W24: =W20*$D24 -> -59123.976 | ... BD24: =BD20*$D24 -> -82104.879
C26: Laser Treatments | D26: Min | E26: Max | F26: Growth Rate
C27: Laser Number of Treatments | D27: 15 | E27: 350 | F27: 0.02 | I27: 48 | J27: 30 | K27: 50 | L27: 40 | M27: 10 | N27: 0 | O27: 17 | P27: =MIN(MAX($D27,O27)*(1+$F27)*P$9,$E27) -> 17.34 | Q27: =MIN(MAX($D27,P27)*(1+$F27)*Q$9,$E27) -> 17.6868 | R27: =MIN(MAX($D27,Q27)*(1+$F27)*R$9,$E27) -> 18.040536 | S27: =MIN(MAX($D27,R27)*(1+$F27)*S$9,$E27) -> 18.401347 | T27: =MIN(MAX($D27,S27)*(1+$F27)*T$9,$E27) -> 18.769374 | U27: =MIN(MAX($D27,T27)*(1+$F27)*U$9,$E27) -> 19.144761 | V27: =MIN(MAX($D27,U27)*(1+$F27)*V$9,$E27) -> 19.527656 | W27: =MIN(MAX($D27,V27)*(1+$F27)*W$9,$E27) -> 19.918209 | ... BD27: =MIN(MAX($D27,BC27)*(1+$F27)*BD$9,$E27) -> 38.287408
C28: Average Revenue / Treatment | D28: =SUM(I28:O28)/7 -> 654.14286 | E28: 2775 | F28: 0 | I28: 750 | J28: 574 | K28: 565 | L28: 691 | M28: 717 | N28: 750 | O28: 532 | P28: =MIN(MAX($D28,O28)*(1+$F28)*P$9,$E28) -> 654.14286 | Q28: =MIN(MAX($D28,P28)*(1+$F28)*Q$9,$E28) -> 654.14286 | R28: =MIN(MAX($D28,Q28)*(1+$F28)*R$9,$E28) -> 654.14286 | S28: =MIN(MAX($D28,R28)*(1+$F28)*S$9,$E28) -> 654.14286 | T28: =MIN(MAX($D28,S28)*(1+$F28)*T$9,$E28) -> 654.14286 | U28: =MIN(MAX($D28,T28)*(1+$F28)*U$9,$E28) -> 654.14286 | V28: =MIN(MAX($D28,U28)*(1+$F28)*V$9,$E28) -> 654.14286 | W28: =MIN(MAX($D28,V28)*(1+$F28)*W$9,$E28) -> 654.14286 | ... BD28: =MIN(MAX($D28,BC28)*(1+$F28)*BD$9,$E28) -> 654.14286
C29: Laser Treatment Revenue | I29: =I27*I28 -> 36000 | J29: =J27*J28 -> 17220 | K29: =K27*K28 -> 28250 | L29: =L27*L28 -> 27640 | M29: =M27*M28 -> 7170 | N29: =N27*N28 -> 0 | O29: =O27*O28 -> 9044 | P29: =P27*P28 -> 11342.837 | ... BD29: =BD27*BD28 -> 25045.434
C31: Hyperthermia (mEHT) 1 | D31: Min | E31: Max | F31: Growth Rate
C32: mEHT Number of Sessions | D32: 80 | E32: 208 | F32: 0.05 | I32: 147 | J32: 127.5 | K32: 166 | L32: 132 | M32: 79.5 | N32: 102 | O32: 100.5 | P32: =MIN(MAX($D32,O32)*(1+$F32)*P$9,$E32) -> 105.525 | Q32: =MIN(MAX($D32,P32)*(1+$F32)*Q$9,$E32) -> 110.80125 | R32: =MIN(MAX($D32,Q32)*(1+$F32)*R$9,$E32) -> 116.34131 | S32: =MIN(MAX($D32,R32)*(1+$F32)*S$9,$E32) -> 122.15838 | T32: =MIN(MAX($D32,S32)*(1+$F32)*T$9,$E32) -> 128.2663 | U32: =MIN(MAX($D32,T32)*(1+$F32)*U$9,$E32) -> 134.67961 | V32: =MIN(MAX($D32,U32)*(1+$F32)*V$9,$E32) -> 141.41359 | W32: =MIN(MAX($D32,V32)*(1+$F32)*W$9,$E32) -> 148.48427 | ... BD32: =MIN(MAX($D32,BC32)*(1+$F32)*BD$9,$E32) -> 208
C33: Average Revenue / Session | D33: 3091 | E33: 3555 | F33: 0 | I33: =3555/1.15 -> 3091.3043 | J33: 3091 | K33: =MIN(MAX($D33,J33)*(1+$F33)*K$9,$E33) -> 3091 | L33: =MIN(MAX($D33,K33)*(1+$F33)*L$9,$E33) -> 3091 | M33: =MIN(MAX($D33,L33)*(1+$F33)*M$9,$E33) -> 3091 | N33: =MIN(MAX($D33,M33)*(1+$F33)*N$9,$E33) -> 3091 | O33: =MIN(MAX($D33,N33)*(1+$F33)*O$9,$E33) -> 3091 | P33: =MIN(MAX($D33,O33)*(1+$F33)*P$9,$E33) -> 3091 | Q33: =MIN(MAX($D33,P33)*(1+$F33)*Q$9,$E33) -> 3091 | R33: =MIN(MAX($D33,Q33)*(1+$F33)*R$9,$E33) -> 3091 | ... BD33: =MIN(MAX($D33,BC33)*(1+$F33)*BD$9,$E33) -> 3091
C34: Hyperthermia Session Revenue | I34: =I32*I33 -> 454421.74 | J34: =J32*J33 -> 394102.5 | K34: =K32*K33 -> 513106 | L34: =L32*L33 -> 408012 | M34: =M32*M33 -> 245734.5 | N34: =N32*N33 -> 315282 | O34: =O32*O33 -> 310645.5 | P34: =P32*P33 -> 326177.78 | ... BD34: =BD32*BD33 -> 642928
C36: Hyperthermia (mEHT) 2
C37: mEHT 2 Treatment commencement | D37: =R4 -> 45961 | I37: =IF(I4=$D$37,1,0) -> 0 | J37: =IF(J4>=$D$37,1,0) -> 0 | K37: =IF(K4>=$D$37,1,0) -> 0 | L37: =IF(L4>=$D$37,1,0) -> 0 | M37: =IF(M4>=$D$37,1,0) -> 0 | N37: =IF(N4>=$D$37,1,0) -> 0 | O37: =IF(O4>=$D$37,1,0) -> 0 | P37: =IF(P4>=$D$37,1,0) -> 0 | Q37: =IF(Q4>=$D$37,1,0) -> 0 | ... BD37: =IF(BD4>=$D$37,1,0) -> 1
D38: Min | E38: Max | F38: Growth Rate
C39: mEHT 2 Number of Sessions | D39: 30 | E39: 208 | F39: 0.05 | I39: =MIN(MAX($D39,H39)*(1+$F39)*I$37,$E39) -> 0 | J39: =MIN(MAX($D39,I39)*(1+$F39)*J$37,$E39) -> 0 | K39: =MIN(MAX($D39,J39)*(1+$F39)*K$37,$E39) -> 0 | L39: =MIN(MAX($D39,K39)*(1+$F39)*L$37,$E39) -> 0 | M39: =MIN(MAX($D39,L39)*(1+$F39)*M$37,$E39) -> 0 | N39: =MIN(MAX($D39,M39)*(1+$F39)*N$37,$E39) -> 0 | O39: =MIN(MAX($D39,N39)*(1+$F39)*O$37,$E39) -> 0 | P39: =MIN(MAX($D39,O39)*(1+$F39)*P$37,$E39) -> 0 | ... BD39: =MIN(MAX($D39,BC39)*(1+$F39)*BD$37,$E39) -> 201.14253
C40: Average Revenue / Session | D40: 3555 | E40: 3555 | F40: 0 | I40: =MIN(MAX($D40,H40)*(1+$F40)*I$37,$E40) -> 0 | J40: =MIN(MAX($D40,I40)*(1+$F40)*J$37,$E40) -> 0 | K40: =MIN(MAX($D40,J40)*(1+$F40)*K$37,$E40) -> 0 | L40: =MIN(MAX($D40,K40)*(1+$F40)*L$37,$E40) -> 0 | M40: =MIN(MAX($D40,L40)*(1+$F40)*M$37,$E40) -> 0 | N40: =MIN(MAX($D40,M40)*(1+$F40)*N$37,$E40) -> 0 | O40: =MIN(MAX($D40,N40)*(1+$F40)*O$37,$E40) -> 0 | P40: =MIN(MAX($D40,O40)*(1+$F40)*P$37,$E40) -> 0 | ... BD40: =MIN(MAX($D40,BC40)*(1+$F40)*BD$37,$E40) -> 3555
C41: Hyperthermia 2 Session Revenue | I41: =I39*I40 -> 0 | J41: =J39*J40 -> 0 | K41: =K39*K40 -> 0 | L41: =L39*L40 -> 0 | M41: =M39*M40 -> 0 | N41: =N39*N40 -> 0 | O41: =O39*O40 -> 0 | P41: =P39*P40 -> 0 | ... BD41: =BD39*BD40 -> 715061.71
C43: HBOT 1
C44: HBOT 1 Sessions commencement | D44: =T4 -> 46022 | I44: =IF(I4>=$D$44,1,0) -> 0 | J44: =IF(J4>=$D$44,1,0) -> 0 | K44: =IF(K4>=$D$44,1,0) -> 0 | L44: =IF(L4>=$D$44,1,0) -> 0 | M44: =IF(M4>=$D$44,1,0) -> 0 | N44: =IF(N4>=$D$44,1,0) -> 0 | O44: =IF(O4>=$D$44,1,0) -> 0 | P44: =IF(P4>=$D$44,1,0) -> 0 | ... BD44: =IF(BD4>=$D$44,1,0) -> 1
E45: Max | F45: Growth Rate
C46: HBOT 1 Number of Sessions | D46: 16 | E46: 120 | F46: 0.05 | I46: =MIN(MAX($D46,H46)*(1+$F46)*I$44,$E46) -> 0 | J46: =MIN(MAX($D46,I46)*(1+$F46)*J$44,$E46) -> 0 | K46: =MIN(MAX($D46,J46)*(1+$F46)*K$44,$E46) -> 0 | L46: =MIN(MAX($D46,K46)*(1+$F46)*L$44,$E46) -> 0 | M46: =MIN(MAX($D46,L46)*(1+$F46)*M$44,$E46) -> 0 | N46: =MIN(MAX($D46,M46)*(1+$F46)*N$44,$E46) -> 0 | O46: =MIN(MAX($D46,N46)*(1+$F46)*O$44,$E46) -> 0 | P46: =MIN(MAX($D46,O46)*(1+$F46)*P$44,$E46) -> 0 | ... BD46: =MIN(MAX($D46,BC46)*(1+$F46)*BD$44,$E46) -> 97.302511
C47: Average Revenue / Session | D47: 2500 | E47: 2500 | F47: 0 | I47: =MIN(MAX($D47,H47)*(1+$F47)*I$44,$E47) -> 0 | J47: =MIN(MAX($D47,I47)*(1+$F47)*J$44,$E47) -> 0 | K47: =MIN(MAX($D47,J47)*(1+$F47)*K$44,$E47) -> 0 | L47: =MIN(MAX($D47,K47)*(1+$F47)*L$44,$E47) -> 0 | M47: =MIN(MAX($D47,L47)*(1+$F47)*M$44,$E47) -> 0 | N47: =MIN(MAX($D47,M47)*(1+$F47)*N$44,$E47) -> 0 | O47: =MIN(MAX($D47,N47)*(1+$F47)*O$44,$E47) -> 0 | P47: =MIN(MAX($D47,O47)*(1+$F47)*P$44,$E47) -> 0 | ... BD47: =MIN(MAX($D47,BC47)*(1+$F47)*BD$44,$E47) -> 2500
C48: HBOT 1 Session Revenue | I48: =I46*I47 -> 0 | J48: =J46*J47 -> 0 | K48: =K46*K47 -> 0 | L48: =L46*L47 -> 0 | M48: =M46*M47 -> 0 | N48: =N46*N47 -> 0 | O48: =O46*O47 -> 0 | P48: =P46*P47 -> 0 | ... BD48: =BD46*BD47 -> 243256.28
C50: HBOT 2
C51: HBOT 2 Sessions commencement | D51: 0 | I51: =IF(I4>=$D$51,1,0) -> 1 | J51: =IF(J4>=$D$51,1,0) -> 1 | K51: =IF(K4>=$D$51,1,0) -> 1 | L51: =IF(L4>=$D$51,1,0) -> 1 | M51: =IF(M4>=$D$51,1,0) -> 1 | N51: =IF(N4>=$D$51,1,0) -> 1 | O51: =IF(O4>=$D$51,1,0) -> 1 | P51: =IF(P4>=$D$51,1,0) -> 1 | ... BD51: =IF(BD4>=$D$51,1,0) -> 1
D52: Min | E52: Max | F52: Growth Rate
C53: HBOT 2 Number of Sessions | F53: 0 | I53: =MIN(MAX($D53,H53)*(1+$F53)*I$51,$E53) -> 0 | J53: =MIN(MAX($D53,I53)*(1+$F53)*J$51,$E53) -> 0 | K53: =MIN(MAX($D53,J53)*(1+$F53)*K$51,$E53) -> 0 | L53: =MIN(MAX($D53,K53)*(1+$F53)*L$51,$E53) -> 0 | M53: =MIN(MAX($D53,L53)*(1+$F53)*M$51,$E53) -> 0 | N53: =MIN(MAX($D53,M53)*(1+$F53)*N$51,$E53) -> 0 | O53: =MIN(MAX($D53,N53)*(1+$F53)*O$51,$E53) -> 0 | P53: =MIN(MAX($D53,O53)*(1+$F53)*P$51,$E53) -> 0 | ... BD53: =MIN(MAX($D53,BC53)*(1+$F53)*BD$51,$E53) -> 0
C54: Average Revenue / Session | F54: 0 | I54: =MIN(MAX($D54,H54)*(1+$F54)*I$51,$E54) -> 0 | J54: =MIN(MAX($D54,I54)*(1+$F54)*J$51,$E54) -> 0 | K54: =MIN(MAX($D54,J54)*(1+$F54)*K$51,$E54) -> 0 | L54: =MIN(MAX($D54,K54)*(1+$F54)*L$51,$E54) -> 0 | M54: =MIN(MAX($D54,L54)*(1+$F54)*M$51,$E54) -> 0 | N54: =MIN(MAX($D54,M54)*(1+$F54)*N$51,$E54) -> 0 | O54: =MIN(MAX($D54,N54)*(1+$F54)*O$51,$E54) -> 0 | P54: =MIN(MAX($D54,O54)*(1+$F54)*P$51,$E54) -> 0 | ... BD54: =MIN(MAX($D54,BC54)*(1+$F54)*BD$51,$E54) -> 0
C55: HBOT 2 Session Revenue | I55: =I53*I54 -> 0 | J55: =J53*J54 -> 0 | K55: =K53*K54 -> 0 | L55: =L53*L54 -> 0 | M55: =M53*M54 -> 0 | N55: =N53*N54 -> 0 | O55: =O53*O54 -> 0 | P55: =P53*P54 -> 0 | ... BD55: =BD53*BD54 -> 0
C57: Photodynamic Therapy (PDT) Low
C58: PDT Treatment Commencement | D58: =I4 -> 45688 | I58: =IF(I4>=$D$58,1,0) -> 1 | J58: =IF(J4>=$D$58,1,0) -> 1 | K58: =IF(K4>=$D$58,1,0) -> 1 | L58: =IF(L4>=$D$58,1,0) -> 1 | M58: =IF(M4>=$D$58,1,0) -> 1 | N58: =IF(N4>=$D$58,1,0) -> 1 | O58: =IF(O4>=$D$58,1,0) -> 1 | P58: =IF(P4>=$D$58,1,0) -> 1 | ... BD58: =IF(BD4>=$D$58,1,0) -> 1
D59: Min | E59: Max | F59: Growth Rate
C60: PDT Low Number of Treatments | D60: 2 | E60: 5 | F60: 0.025 | I60: 6 | J60: 4 | K60: 0 | L60: 7 | M60: 4 | N60: 3 | O60: 0 | P60: =MIN(MAX($D60,O60)*(1+$F60)*P$58,$E60) -> 2.05 | Q60: =MIN(MAX($D60,P60)*(1+$F60)*Q$58,$E60) -> 2.10125 | R60: =MIN(MAX($D60,Q60)*(1+$F60)*R$58,$E60) -> 2.1537812 | S60: =MIN(MAX($D60,R60)*(1+$F60)*S$58,$E60) -> 2.2076258 | T60: =MIN(MAX($D60,S60)*(1+$F60)*T$58,$E60) -> 2.2628164 | U60: =MIN(MAX($D60,T60)*(1+$F60)*U$58,$E60) -> 2.3193868 | V60: =MIN(MAX($D60,U60)*(1+$F60)*V$58,$E60) -> 2.3773715 | W60: =MIN(MAX($D60,V60)*(1+$F60)*W$58,$E60) -> 2.4368058 | ... BD60: =MIN(MAX($D60,BC60)*(1+$F60)*BD$58,$E60) -> 5
C61: Average Revenue / Treatment / month | D61: 80000 | E61: 100000 | F61: 0.02 | I61: 103744.13 | J61: 104075.75 | K61: =MIN(MAX($D61,J61)*(1+$F61)*K$58,$E61) -> 100000 | L61: 93779 | M61: 87514 | N61: 97659 | O61: =MIN(MAX($D61,N61)*(1+$F61)*O$58,$E61) -> 99612.18 | P61: =MIN(MAX($D61,O61)*(1+$F61)*P$58,$E61) -> 100000 | Q61: =MIN(MAX($D61,P61)*(1+$F61)*Q$58,$E61) -> 100000 | R61: =MIN(MAX($D61,Q61)*(1+$F61)*R$58,$E61) -> 100000 | S61: =MIN(MAX($D61,R61)*(1+$F61)*S$58,$E61) -> 100000 | T61: =MIN(MAX($D61,S61)*(1+$F61)*T$58,$E61) -> 100000 | U61: =MIN(MAX($D61,T61)*(1+$F61)*U$58,$E61) -> 100000 | V61: =MIN(MAX($D61,U61)*(1+$F61)*V$58,$E61) -> 100000 | ... BD61: =MIN(MAX($D61,BC61)*(1+$F61)*BD$58,$E61) -> 100000
C62: PDT Low Treatment Revenue | I62: =I60*I61 -> 622464.76 | J62: =J60*J61 -> 416303 | K62: =K60*K61 -> 0 | L62: =L60*L61 -> 656453 | M62: =M60*M61 -> 350056 | N62: =N60*N61 -> 292977 | O62: =O60*O61 -> 0 | P62: =P60*P61 -> 205000 | ... BD62: =BD60*BD61 -> 500000
C64: PDT Low COS | D64: -8500 | I64: =I60*$D$64 -> -51000 | J64: =J60*$D$64 -> -34000 | K64: =K60*$D$64 -> 0 | L64: =-L62*0.1 -> -65645.3 | M64: =-M62*0.1 -> -35005.6 | N64: =-N62*0.1 -> -29297.7 | O64: =-O62*0.1 -> 0 | P64: =P60*$D$64 -> -17425 | Q64: =Q60*$D$64 -> -17860.625 | R64: =R60*$D$64 -> -18307.141 | S64: =S60*$D$64 -> -18764.819 | T64: =T60*$D$64 -> -19233.94 | U64: =U60*$D$64 -> -19714.788 | V64: =V60*$D$64 -> -20207.658 | W64: =W60*$D$64 -> -20712.849 | ... BD64: =BD60*$D$64 -> -42500
C66: Photodynamic Therapy (PDT) High
D67: Min | E67: Max | F67: Growth Rate | H67: 0
C68: PDT High Number of Patients | D68: =SUM(I68:O68)/7 -> 0.85714286 | E68: 2 | F68: 0 | H68: 0 | I68: 0 | J68: 0 | K68: 3 | L68: 0 | M68: 0 | N68: 0 | O68: 3 | P68: =MIN(MAX($D68,O68)*(1+$F68)*P$58,$E68) -> 2 | Q68: =MIN(MAX($D68,P68)*(1+$F68)*Q$58,$E68) -> 2 | R68: =MIN(MAX($D68,Q68)*(1+$F68)*R$58,$E68) -> 2 | S68: =MIN(MAX($D68,R68)*(1+$F68)*S$58,$E68) -> 2 | T68: =MIN(MAX($D68,S68)*(1+$F68)*T$58,$E68) -> 2 | U68: =MIN(MAX($D68,T68)*(1+$F68)*U$58,$E68) -> 2 | V68: =MIN(MAX($D68,U68)*(1+$F68)*V$58,$E68) -> 2 | W68: =MIN(MAX($D68,V68)*(1+$F68)*W$58,$E68) -> 2 | ... BD68: =MIN(MAX($D68,BC68)*(1+$F68)*BD$58,$E68) -> 2
C69: Average Revenue / Patient / month | D69: 120000 | E69: 120000 | F69: 0 | H69: 0 | I69: =MIN(MAX($D69,H69)*(1+$F69)*I$58,$E69) -> 120000 | J69: =MIN(MAX($D69,I69)*(1+$F69)*J$58,$E69) -> 120000 | K69: 176256.67 | L69: =MIN(MAX($D69,K69)*(1+$F69)*L$58,$E69) -> 120000 | M69: =MIN(MAX($D69,L69)*(1+$F69)*M$58,$E69) -> 120000 | N69: =MIN(MAX($D69,M69)*(1+$F69)*N$58,$E69) -> 120000 | O69: 118225 | P69: =MIN(MAX($D69,O69)*(1+$F69)*P$58,$E69) -> 120000 | Q69: =MIN(MAX($D69,P69)*(1+$F69)*Q$58,$E69) -> 120000 | R69: =MIN(MAX($D69,Q69)*(1+$F69)*R$58,$E69) -> 120000 | S69: =MIN(MAX($D69,R69)*(1+$F69)*S$58,$E69) -> 120000 | T69: =MIN(MAX($D69,S69)*(1+$F69)*T$58,$E69) -> 120000 | U69: =MIN(MAX($D69,T69)*(1+$F69)*U$58,$E69) -> 120000 | V69: =MIN(MAX($D69,U69)*(1+$F69)*V$58,$E69) -> 120000 | W69: =MIN(MAX($D69,V69)*(1+$F69)*W$58,$E69) -> 120000 | ... BD69: =MIN(MAX($D69,BC69)*(1+$F69)*BD$58,$E69) -> 120000
C70: PDT High Treatment Revenue | H70: 0 | I70: =I68*I69 -> 0 | J70: =J68*J69 -> 0 | K70: =K68*K69 -> 528770 | L70: =L68*L69 -> 0 | M70: =M68*M69 -> 0 | N70: =N68*N69 -> 0 | O70: =O68*O69 -> 354675 | P70: =P68*P69 -> 240000 | ... BD70: =BD68*BD69 -> 240000
H71: 0
C72: PDT High COS | D72: =D69*-0.2 -> -24000 | I72: =I68*$D72 -> 0 | J72: =J68*$D72 -> 0 | K72: =K68*$D72 -> -72000 | L72: =-L70*0.2 -> 0 | M72: =-M70*0.2 -> 0 | N72: =-N70*0.2 -> 0 | O72: =-O70*0.2 -> -70935 | P72: =P68*$D72 -> -48000 | Q72: =Q68*$D72 -> -48000 | R72: =R68*$D72 -> -48000 | S72: =S68*$D72 -> -48000 | T72: =T68*$D72 -> -48000 | U72: =U68*$D72 -> -48000 | V72: =V68*$D72 -> -48000 | W72: =W68*$D72 -> -48000 | ... BD72: =BD68*$D72 -> -48000
C74: Immunotherapy
C75: Immunotherapy commencement | D75: =I4 -> 45688 | I75: =IF(I4>=$D$75,1,0) -> 1 | J75: =IF(J4>=$D$75,1,0) -> 1 | K75: =IF(K4>=$D$75,1,0) -> 1 | L75: =IF(L4>=$D$75,1,0) -> 1 | M75: =IF(M4>=$D$75,1,0) -> 1 | N75: =IF(N4>=$D$75,1,0) -> 1 | O75: =IF(O4>=$D$75,1,0) -> 1 | P75: =IF(P4>=$D$75,1,0) -> 1 | ... BD75: =IF(BD4>=$D$75,1,0) -> 1
D76: Min | E76: Max | F76: Growth Rate
C77: Immunotherapy Number of Treatments | D77: 5 | E77: 32 | F77: 0.01 | I77: 4 | J77: 4 | K77: 8 | L77: 5 | M77: 9 | N77: 8 | O77: 8 | P77: =MIN(MAX($D77,O77)*(1+$F77)*P$75,$E77) -> 8.08 | Q77: =MIN(MAX($D77,P77)*(1+$F77)*Q$75,$E77) -> 8.1608 | R77: =MIN(MAX($D77,Q77)*(1+$F77)*R$75,$E77) -> 8.242408 | S77: =MIN(MAX($D77,R77)*(1+$F77)*S$75,$E77) -> 8.3248321 | T77: =MIN(MAX($D77,S77)*(1+$F77)*T$75,$E77) -> 8.4080804 | U77: =MIN(MAX($D77,T77)*(1+$F77)*U$75,$E77) -> 8.4921612 | V77: =MIN(MAX($D77,U77)*(1+$F77)*V$75,$E77) -> 8.5770828 | W77: =MIN(MAX($D77,V77)*(1+$F77)*W$75,$E77) -> 8.6628536 | ... BD77: =MIN(MAX($D77,BC77)*(1+$F77)*BD$75,$E77) -> 12.030019
C78: Average Revenue / Treatments / month | D78: =SUM(I78:O78)/7 -> 65023.143 | E78: 110000 | F78: 0.01 | I78: 77602 | J78: 87203 | K78: 61000 | L78: 73270 | M78: 65168 | N78: 60565 | O78: 30354 | P78: =MIN(MAX($D78,O78)*(1+$F78)*P$75,$E78) -> 65673.374 | Q78: =MIN(MAX($D78,P78)*(1+$F78)*Q$75,$E78) -> 66330.108 | R78: =MIN(MAX($D78,Q78)*(1+$F78)*R$75,$E78) -> 66993.409 | S78: =MIN(MAX($D78,R78)*(1+$F78)*S$75,$E78) -> 67663.343 | T78: =MIN(MAX($D78,S78)*(1+$F78)*T$75,$E78) -> 68339.977 | U78: =MIN(MAX($D78,T78)*(1+$F78)*U$75,$E78) -> 69023.376 | V78: =MIN(MAX($D78,U78)*(1+$F78)*V$75,$E78) -> 69713.61 | W78: =MIN(MAX($D78,V78)*(1+$F78)*W$75,$E78) -> 70410.746 | ... BD78: =MIN(MAX($D78,BC78)*(1+$F78)*BD$75,$E78) -> 97778.705
C79: Immunotherapy Treatments Revenue | I79: =I77*I78 -> 310408 | J79: =J77*J78 -> 348812 | K79: =K77*K78 -> 488000 | L79: =L77*L78 -> 366350 | M79: =M77*M78 -> 586512 | N79: =N77*N78 -> 484520 | O79: =O77*O78 -> 242832 | P79: =P77*P78 -> 530640.86 | ... BD79: =BD77*BD78 -> 1176279.7
C81: Immunotherapy COS | D81: =-(D78)*0.87 -> -56570.134 | I81: =-I$79*0.87 -> -270054.96 | J81: =-J$79*0.87 -> -303466.44 | K81: =-K$79*0.87 -> -424560 | L81: =-L$79*0.87 -> -318724.5 | M81: =-M$79*0.87 -> -510265.44 | N81: =-N$79*0.87 -> -421532.4 | O81: =-O$79*0.87 -> -211263.84 | P81: =P77*$D81 -> -457086.69 | Q81: =Q77*$D81 -> -461657.55 | R81: =R77*$D81 -> -466274.13 | S81: =S77*$D81 -> -470936.87 | T81: =T77*$D81 -> -475646.24 | U81: =U77*$D81 -> -480402.7 | V81: =V77*$D81 -> -485206.73 | W81: =W77*$D81 -> -490058.79 | ... BD81: =BD77*$D81 -> -680539.79
C83: Chemotherapy
C84: Chemotherapy commencement | D84: =I4 -> 45688 | I84: =IF(I12>=$D$75,1,0) -> 0 | J84: =IF(J12>=$D$75,1,0) -> 0 | K84: =IF(K12>=$D$75,1,0) -> 0 | L84: =IF(L12>=$D$75,1,0) -> 0 | M84: =IF(M12>=$D$75,1,0) -> 0 | N84: =IF(N12>=$D$75,1,0) -> 0 | O84: =IF(O12>=$D$75,1,0) -> 0 | P84: =IF(P12>=$D$75,1,0) -> 0 | ... BD84: =IF(BD12>=$D$75,1,0) -> 0
D85: Min | E85: Max | F85: Growth Rate
C86: Chemotherapy Number of Treatments | D86: 0 | E86: 32 | F86: 0.01 | I86: 7 | J86: 7 | K86: 12 | L86: 19 | M86: 18 | N86: 13 | O86: 7 | P86: =MIN(MAX($D86,O86)*(1+$F86)*P$75,$E86) -> 7.07 | Q86: =MIN(MAX($D86,P86)*(1+$F86)*Q$75,$E86) -> 7.1407 | R86: =MIN(MAX($D86,Q86)*(1+$F86)*R$75,$E86) -> 7.212107 | S86: =MIN(MAX($D86,R86)*(1+$F86)*S$75,$E86) -> 7.2842281 | T86: =MIN(MAX($D86,S86)*(1+$F86)*T$75,$E86) -> 7.3570704 | U86: =MIN(MAX($D86,T86)*(1+$F86)*U$75,$E86) -> 7.4306411 | V86: =MIN(MAX($D86,U86)*(1+$F86)*V$75,$E86) -> 7.5049475 | W86: =MIN(MAX($D86,V86)*(1+$F86)*W$75,$E86) -> 7.5799969 | ... BD86: =MIN(MAX($D86,BC86)*(1+$F86)*BD$75,$E86) -> 10.526267
C87: Average Revenue / Treatments / month | D87: =SUM(I87:O87)/7 -> 19828.571 | E87: 35000 | F87: 0.01 | I87: 17299 | J87: 14557 | K87: 15482 | L87: 10698 | M87: 50868 | N87: 6848 | O87: 23048 | P87: =MIN(MAX($D87,O87)*(1+$F87)*P$75,$E87) -> 23278.48 | Q87: =MIN(MAX($D87,P87)*(1+$F87)*Q$75,$E87) -> 23511.265 | R87: =MIN(MAX($D87,Q87)*(1+$F87)*R$75,$E87) -> 23746.377 | S87: =MIN(MAX($D87,R87)*(1+$F87)*S$75,$E87) -> 23983.841 | T87: =MIN(MAX($D87,S87)*(1+$F87)*T$75,$E87) -> 24223.68 | U87: =MIN(MAX($D87,T87)*(1+$F87)*U$75,$E87) -> 24465.916 | V87: =MIN(MAX($D87,U87)*(1+$F87)*V$75,$E87) -> 24710.576 | W87: =MIN(MAX($D87,V87)*(1+$F87)*W$75,$E87) -> 24957.681 | ... BD87: =MIN(MAX($D87,BC87)*(1+$F87)*BD$75,$E87) -> 34658.485
C88: Chemotherapy Treatments Revenue | I88: =I86*I87 -> 121093 | J88: =J86*J87 -> 101899 | K88: =K86*K87 -> 185784 | L88: =L86*L87 -> 203262 | M88: =M86*M87 -> 915624 | N88: =N86*N87 -> 89024 | O88: =O86*O87 -> 161336 | P88: =P86*P87 -> 164578.85 | ... BD88: =BD86*BD87 -> 364824.45
C90: Chemotherapy COS | D90: =-(D87)*0.3 -> -5948.5714 | I90: =-I$88*0.3 -> -36327.9 | J90: =-J$88*0.3 -> -30569.7 | K90: =-K$88*0.3 -> -55735.2 | L90: =-L$88*0.3 -> -60978.6 | M90: =-M$88*0.3 -> -274687.2 | N90: =-N$88*0.3 -> -26707.2 | O90: =-O$88*0.3 -> -48400.8 | P90: =P86*$D90 -> -42056.4 | Q90: =Q86*$D90 -> -42476.964 | R90: =R86*$D90 -> -42901.734 | S90: =S86*$D90 -> -43330.751 | T90: =T86*$D90 -> -43764.058 | U90: =U86*$D90 -> -44201.699 | V90: =V86*$D90 -> -44643.716 | W90: =W86*$D90 -> -45090.153 | ... BD90: =BD86*$D90 -> -62616.249
C92: Consultations | D92: Min | E92: Max | F92: Growth Rate
C93: Consultation Number of Sessions | D93: 15 | E93: 130 | F93: 0.02 | H93: 0 | I93: 42.3 | J93: 48 | K93: 26.8 | L93: 20.6 | M93: 26.7 | N93: 20 | O93: 15.4 | P93: =MIN(MAX($D93,O93)*(1+$F93)*P$9,$E93) -> 15.708 | Q93: =MIN(MAX($D93,P93)*(1+$F93)*Q$9,$E93) -> 16.02216 | R93: =MIN(MAX($D93,Q93)*(1+$F93)*R$9,$E93) -> 16.342603 | S93: =MIN(MAX($D93,R93)*(1+$F93)*S$9,$E93) -> 16.669455 | T93: =MIN(MAX($D93,S93)*(1+$F93)*T$9,$E93) -> 17.002844 | U93: =MIN(MAX($D93,T93)*(1+$F93)*U$9,$E93) -> 17.342901 | V93: =MIN(MAX($D93,U93)*(1+$F93)*V$9,$E93) -> 17.689759 | W93: =MIN(MAX($D93,V93)*(1+$F93)*W$9,$E93) -> 18.043554 | ... BD93: =MIN(MAX($D93,BC93)*(1+$F93)*BD$9,$E93) -> 34.683887
C94: Average Revenue / Session | D94: 3650 | E94: 4225 | F94: 0.02 | H94: 0 | I94: 2774 | J94: 2774 | K94: 2774 | L94: 2774 | M94: 2774 | N94: 2774 | O94: 2774 | P94: =MIN(MAX($D94,O94)*(1+$F94)*P$9,$E94) -> 3723 | Q94: =MIN(MAX($D94,P94)*(1+$F94)*Q$9,$E94) -> 3797.46 | R94: =MIN(MAX($D94,Q94)*(1+$F94)*R$9,$E94) -> 3873.4092 | S94: =MIN(MAX($D94,R94)*(1+$F94)*S$9,$E94) -> 3950.8774 | T94: =MIN(MAX($D94,S94)*(1+$F94)*T$9,$E94) -> 4029.8949 | U94: =MIN(MAX($D94,T94)*(1+$F94)*U$9,$E94) -> 4110.4928 | V94: =MIN(MAX($D94,U94)*(1+$F94)*V$9,$E94) -> 4192.7027 | W94: =MIN(MAX($D94,V94)*(1+$F94)*W$9,$E94) -> 4225 | ... BD94: =MIN(MAX($D94,BC94)*(1+$F94)*BD$9,$E94) -> 4225
C95: Consultation Session Revenue | H95: 0 | I95: =I93*I94 -> 117340.2 | J95: =J93*J94 -> 133152 | K95: =K93*K94 -> 74343.2 | L95: =L93*L94 -> 57144.4 | M95: =M93*M94 -> 74065.8 | N95: =N93*N94 -> 55480 | O95: =O93*O94 -> 42719.6 | P95: =P93*P94 -> 58480.884 | ... BD95: =BD93*BD94 -> 146539.42
H96: 0
C97: Supplements | D97: Min | E97: Max | F97: Growth Rate | H97: 0
C98: Supplements Number of Patients | D98: =D93 -> 15 | E98: =E93 -> 130 | F98: 0.05 | H98: 0 | P98: =MIN(MAX($D98,O98)*(1+$F98)*P$9,$E98) -> 15.75 | Q98: =MIN(MAX($D98,P98)*(1+$F98)*Q$9,$E98) -> 16.5375 | R98: =MIN(MAX($D98,Q98)*(1+$F98)*R$9,$E98) -> 17.364375 | S98: =MIN(MAX($D98,R98)*(1+$F98)*S$9,$E98) -> 18.232594 | T98: =MIN(MAX($D98,S98)*(1+$F98)*T$9,$E98) -> 19.144223 | U98: =MIN(MAX($D98,T98)*(1+$F98)*U$9,$E98) -> 20.101435 | V98: =MIN(MAX($D98,U98)*(1+$F98)*V$9,$E98) -> 21.106506 | W98: =MIN(MAX($D98,V98)*(1+$F98)*W$9,$E98) -> 22.161832 | ... BD98: =MIN(MAX($D98,BC98)*(1+$F98)*BD$9,$E98) -> 110.87982
C99: Average Revenue / Patient / month | D99: 3000 | E99: 4000 | F99: 0.02 | H99: 0 | P99: =MIN(MAX($D99,O99)*(1+$F99)*P$9,$E99) -> 3060 | Q99: =MIN(MAX($D99,P99)*(1+$F99)*Q$9,$E99) -> 3121.2 | R99: =MIN(MAX($D99,Q99)*(1+$F99)*R$9,$E99) -> 3183.624 | S99: =MIN(MAX($D99,R99)*(1+$F99)*S$9,$E99) -> 3247.2965 | T99: =MIN(MAX($D99,S99)*(1+$F99)*T$9,$E99) -> 3312.2424 | U99: =MIN(MAX($D99,T99)*(1+$F99)*U$9,$E99) -> 3378.4873 | V99: =MIN(MAX($D99,U99)*(1+$F99)*V$9,$E99) -> 3446.057 | W99: =MIN(MAX($D99,V99)*(1+$F99)*W$9,$E99) -> 3514.9781 | ... BD99: =MIN(MAX($D99,BC99)*(1+$F99)*BD$9,$E99) -> 4000
C100: Supplements Patient Revenue | H100: 0 | I100: 121685 | J100: 99698 | K100: 120493 | L100: 93722 | M100: 100729 | N100: 73874 | O100: 57077 | P100: =P98*P99 -> 48195 | Q100: =Q98*Q99 -> 51616.845 | R100: =R98*R99 -> 55281.641 | S100: =S98*S99 -> 59206.638 | T100: =T98*T99 -> 63410.309 | U100: =U98*U99 -> 67912.441 | V100: =V98*V99 -> 72734.224 | W100: =W98*W99 -> 77898.354 | ... BD100: =BD98*BD99 -> 443519.29
H101: 0
C102: Supplement Cost of Sales | D102: =-(D99*0.4) -> -1200 | I102: =-I100*0.35 -> -42589.75 | J102: =-J100*0.35 -> -34894.3 | K102: =-K100*0.35 -> -42172.55 | L102: =-L100*0.35 -> -32802.7 | M102: =-M100*0.35 -> -35255.15 | N102: =-N100*0.35 -> -25855.9 | O102: =-O100*0.35 -> -19976.95 | P102: =-P100*0.35 -> -16868.25 | ... BD102: =-BD100*0.35 -> -155231.75
H103: 0
C104: Scripted Medication | D104: Min | E104: Max | F104: Growth Rate | H104: 0
C105: Scripted Medication Number of Patients | D105: =D93 -> 15 | E105: =E93 -> 130 | F105: 0.05 | H105: 0 | P105: =MIN(MAX($D105,O105)*(1+$F105)*P$9,$E105) -> 15.75 | Q105: =MIN(MAX($D105,P105)*(1+$F105)*Q$9,$E105) -> 16.5375 | R105: =MIN(MAX($D105,Q105)*(1+$F105)*R$9,$E105) -> 17.364375 | S105: =MIN(MAX($D105,R105)*(1+$F105)*S$9,$E105) -> 18.232594 | T105: =MIN(MAX($D105,S105)*(1+$F105)*T$9,$E105) -> 19.144223 | U105: =MIN(MAX($D105,T105)*(1+$F105)*U$9,$E105) -> 20.101435 | V105: =MIN(MAX($D105,U105)*(1+$F105)*V$9,$E105) -> 21.106506 | W105: =MIN(MAX($D105,V105)*(1+$F105)*W$9,$E105) -> 22.161832 | ... BD105: =MIN(MAX($D105,BC105)*(1+$F105)*BD$9,$E105) -> 110.87982
C106: Average Revenue / Patient / month | D106: 2545 | E106: 5261 | F106: 0.05 | H106: 0 | P106: =MIN(MAX($D106,O106)*(1+$F106)*P$9,$E106) -> 2672.25 | Q106: =MIN(MAX($D106,P106)*(1+$F106)*Q$9,$E106) -> 2805.8625 | R106: =MIN(MAX($D106,Q106)*(1+$F106)*R$9,$E106) -> 2946.1556 | S106: =MIN(MAX($D106,R106)*(1+$F106)*S$9,$E106) -> 3093.4634 | T106: =MIN(MAX($D106,S106)*(1+$F106)*T$9,$E106) -> 3248.1366 | U106: =MIN(MAX($D106,T106)*(1+$F106)*U$9,$E106) -> 3410.5434 | V106: =MIN(MAX($D106,U106)*(1+$F106)*V$9,$E106) -> 3581.0706 | W106: =MIN(MAX($D106,V106)*(1+$F106)*W$9,$E106) -> 3760.1241 | ... BD106: =MIN(MAX($D106,BC106)*(1+$F106)*BD$9,$E106) -> 5261
C107: Scripted Medication Patient Revenue | H107: 0 | I107: 123834 | J107: 102626 | K107: 93934 | L107: 137037 | M107: 120455 | N107: 144217 | O107: 80536 | P107: =P105*P106 -> 42087.938 | Q107: =Q105*Q106 -> 46401.951 | R107: =R105*R106 -> 51158.151 | S107: =S105*S106 -> 56401.862 | T107: =T105*T106 -> 62183.052 | U107: =U105*U106 -> 68556.815 | V107: =V105*V106 -> 75583.889 | W107: =W105*W106 -> 83331.237 | ... BD107: =BD105*BD106 -> 583338.74
H108: 0
C109: Scripted Medication COS | D109: =-(D106*0.65) -> -1654.25 | I109: =-I107*0.65 -> -80492.1 | J109: =-J107*0.65 -> -66706.9 | K109: =-K107*0.65 -> -61057.1 | L109: =-L107*0.65 -> -89074.05 | M109: =-M107*0.65 -> -78295.75 | N109: =-N107*0.65 -> -93741.05 | O109: =-O107*0.65 -> -52348.4 | P109: =-P107*0.65 -> -27357.159 | ... BD109: =-BD107*0.65 -> -379170.18
C111: DCT | D111: Min | E111: Max | F111: Growth Rate | H111: 0
C112: DCT Number of Patients | D112: 0 | E112: 0 | F112: 0 | H112: 0 | I112: 1 | J112: =MIN(MAX($D112,I112)*(1+$F112)*J$9,$E112) -> 0 | K112: =MIN(MAX($D112,J112)*(1+$F112)*K$9,$E112) -> 0 | L112: =MIN(MAX($D112,K112)*(1+$F112)*L$9,$E112) -> 0 | M112: =MIN(MAX($D112,L112)*(1+$F112)*M$9,$E112) -> 0 | N112: =MIN(MAX($D112,M112)*(1+$F112)*N$9,$E112) -> 0 | O112: =MIN(MAX($D112,N112)*(1+$F112)*O$9,$E112) -> 0 | P112: =MIN(MAX($D112,O112)*(1+$F112)*P$9,$E112) -> 0 | Q112: =MIN(MAX($D112,P112)*(1+$F112)*Q$9,$E112) -> 0 | ... BD112: =MIN(MAX($D112,BC112)*(1+$F112)*BD$9,$E112) -> 0
C113: Average Revenue / Patient / month | D113: 450000 | E113: 450000 | F113: 0 | H113: 0 | I113: 414600 | J113: =MIN(MAX($D113,I113)*(1+$F113)*J$9,$E113) -> 450000 | K113: =MIN(MAX($D113,J113)*(1+$F113)*K$9,$E113) -> 450000 | L113: =MIN(MAX($D113,K113)*(1+$F113)*L$9,$E113) -> 450000 | M113: =MIN(MAX($D113,L113)*(1+$F113)*M$9,$E113) -> 450000 | N113: =MIN(MAX($D113,M113)*(1+$F113)*N$9,$E113) -> 450000 | O113: =MIN(MAX($D113,N113)*(1+$F113)*O$9,$E113) -> 450000 | P113: =MIN(MAX($D113,O113)*(1+$F113)*P$9,$E113) -> 450000 | Q113: =MIN(MAX($D113,P113)*(1+$F113)*Q$9,$E113) -> 450000 | ... BD113: =MIN(MAX($D113,BC113)*(1+$F113)*BD$9,$E113) -> 450000
C114: DCT Patient Revenue | H114: 0 | I114: =I112*I113 -> 414600 | J114: =J112*J113 -> 0 | K114: =K112*K113 -> 0 | L114: =L112*L113 -> 0 | M114: =M112*M113 -> 0 | N114: =N112*N113 -> 0 | O114: =O112*O113 -> 0 | P114: =P112*P113 -> 0 | ... BD114: =BD112*BD113 -> 0
H115: 0
C116: DCT COS | D116: 350000 | I116: =-I113*0.9 -> -373140 | J116: =J112*$D116 -> 0 | K116: =K112*$D116 -> 0 | L116: =L112*$D116 -> 0 | M116: =M112*$D116 -> 0 | N116: =N112*$D116 -> 0 | O116: =O112*$D116 -> 0 | P116: =P112*$D116 -> 0 | Q116: =Q112*$D116 -> 0 | ... BD116: =BD112*$D116 -> 0
C118: Pathcare Rebate | D118: Min | E118: Max | F118: Growth Rate | H118: 0
C119: Pathcare Rebate Number of Tests | D119: 0 | E119: 25 | F119: 0.1 | H119: 0 | I119: =MIN(MAX($D119,H119)*(1+$F119)*I$9,$E119) -> 0 | J119: =MIN(MAX($D119,I119)*(1+$F119)*J$9,$E119) -> 0 | K119: =MIN(MAX($D119,J119)*(1+$F119)*K$9,$E119) -> 0 | L119: =MIN(MAX($D119,K119)*(1+$F119)*L$9,$E119) -> 0 | M119: =MIN(MAX($D119,L119)*(1+$F119)*M$9,$E119) -> 0 | N119: =MIN(MAX($D119,M119)*(1+$F119)*N$9,$E119) -> 0 | O119: =MIN(MAX($D119,N119)*(1+$F119)*O$9,$E119) -> 0 | P119: =MIN(MAX($D119,O119)*(1+$F119)*P$9,$E119) -> 0 | ... BD119: =MIN(MAX($D119,BC119)*(1+$F119)*BD$9,$E119) -> 0
C120: Average Revenue / Tests / month | D120: 6000 | E120: 6000 | F120: 0 | H120: 0 | I120: =MIN(MAX($D120,H120)*(1+$F120)*I$9,$E120) -> 6000 | J120: =MIN(MAX($D120,I120)*(1+$F120)*J$9,$E120) -> 6000 | K120: =MIN(MAX($D120,J120)*(1+$F120)*K$9,$E120) -> 6000 | L120: =MIN(MAX($D120,K120)*(1+$F120)*L$9,$E120) -> 6000 | M120: =MIN(MAX($D120,L120)*(1+$F120)*M$9,$E120) -> 6000 | N120: =MIN(MAX($D120,M120)*(1+$F120)*N$9,$E120) -> 6000 | O120: =MIN(MAX($D120,N120)*(1+$F120)*O$9,$E120) -> 6000 | P120: =MIN(MAX($D120,O120)*(1+$F120)*P$9,$E120) -> 6000 | ... BD120: =MIN(MAX($D120,BC120)*(1+$F120)*BD$9,$E120) -> 6000
C121: Pathcare Rebate Testing Revenue | H121: 0 | I121: =I119*I120 -> 0 | J121: =J119*J120 -> 0 | K121: =K119*K120 -> 0 | L121: =L119*L120 -> 0 | M121: =M119*M120 -> 0 | N121: =N119*N120 -> 0 | O121: =O119*O120 -> 0 | P121: =P119*P120 -> 0 | ... BD121: =BD119*BD120 -> 0
H122: 0
...

Sheet UK P & L
A1: Profit and Loss | K1: Sales by Item
A2: Sanctura Limited | K2: Sanctura Limited
A3: For the month ended 30 November 2025 | K3: 1 November 2025 to 30 November 2025
A5: Account | B5: Actual Nov 2025 | C5: Reforecast Nov 2025 | E5: Year to date | F5: Reforecast YTD | K5: Item | L5: Current Unit Price | M5: Quantity Sold | N5: Total | O5: Average Price
A7: Turnover | K7: Consultation - 1 hour (CON1) | L7: 510 | M7: 1 | N7: 500 | O7: =IF(ISERROR(N7/M7),"",N7/M7) -> 500
A8: Sales | B8: 87974 | C8: ='UK V4'!W260 -> 136170.11 | E8: 492815 | F8: =SUM('UK V4'!O260:W260) -> 753524.19 | K8: Consultation - 15 Minutes (CON6) | L8: 195 | M8: 17 | N8: 3315 | O8: =IF(ISERROR(N8/M8),"",N8/M8) -> 195
A9: Sales - Pathology | B9: 3711 | E9: 5250 | K9: Consultation - 30 min (CON2) | L9: 375 | M9: 27 | N9: 9750 | O9: =IF(ISERROR(N9/M9),"",N9/M9) -> 361.11111
A10: Agency Fees | B10: 210 | E10: 180625 | K10: Endovascular laser therapy - 20Min (ENDO) | L10: 100 | M10: 40 | N10: 4000 | O10: =IF(ISERROR(N10/M10),"",N10/M10) -> 100
A11: Total Turnover | B11: =SUM(B8:B10) -> 91895 | C11: =SUM(C8:C10) -> 136170.11 | E11: =SUM(E8:E10) -> 678690 | F11: =SUM(F8:F10) -> 753524.19 | K11: Hyperbaric Oxygen Therapy Session - 2 ATA 90 Min (HBOT) | L11: 200 | M11: 22 | N11: 4400 | O11: =IF(ISERROR(N11/M11),"",N11/M11) -> 200
K12: Infusion Fee (CON4) | L12: 125 | M12: 70 | N12: 8375 | O12: =IF(ISERROR(N12/M12),"",N12/M12) -> 119.64286
A13: Cost of Sales | K13: mEHT Hyperthermia Treatment - 60 Min (mEHT 60) | L13: 300 | M13: 22 | N13: 5400 | O13: =IF(ISERROR(N13/M13),"",N13/M13) -> 245.45455
A14: Cost of Goods Sold | B14: 7302 | C14: =-SUM('UK V4'!W262:W268) -> 16976.091 | E14: 68706 | F14: =-SUM('UK V4'!O262:W268) -> 102454.28 | K14: mEHT Hyperthermia Treatment - 90 Min (mEHT 90) | L14: 450 | M14: 59 | N14: 24970 | O14: =IF(ISERROR(N14/M14),"",N14/M14) -> 423.22034
A15: Pathology COS | B15: 0 | E15: 1250 | K15: Phlebotomy Fee (CON9) | L15: 69 | M15: 1 | N15: 69 | O15: =IF(ISERROR(N15/M15),"",N15/M15) -> 69
A16: Agency Fees COS | B16: 2557 | E16: 176565 | K16: Pathology Fees | N16: 3711.48
A17: Total Cost of Sales | B17: =SUM(B14:B16) -> 9859 | C17: =SUM(C14:C16) -> 16976.091 | E17: =SUM(E14:E16) -> 246521 | F17: =SUM(F14:F16) -> 102454.28 | K17: Transcranial Photobiomodulation (HEL) | L17: 50 | M17: 3 | N17: 150 | O17: =IF(ISERROR(N17/M17),"",N17/M17) -> 50
K18: Total | M18: =SUM(M7:M17) -> 262 | N18: =SUM(N7:N17) -> 64640.48 | O18: =IF(ISERROR(N18/M18),"",N18/M18) -> 246.71939
A19: Gross Profit | B19: =(B11 - B17) -> 82036 | C19: =(C11 - C17) -> 119194.02 | E19: =(E11 - E17) -> 432169 | F19: =(F11 - F17) -> 651069.92
K20: Summary
K21: Sales by item | N21: =N18 -> 64640.48
A22: Staff Costs: Medical, Admin, Consultants, Director | B22: =SUM(B41:B45) -> 44294.28 | C22: =-'UK V4'!W280 -> 60171.132 | E22: =SUM(E41:E45) -> 202536.9 | F22: =-SUM('UK V4'!O280:W280) -> 332362.73 | K22: Other sales | N22: =27044.56+375 -> 27419.56
A23: Rent | B23: =B66 -> 23750 | C23: =-'UK V4'!W282 -> 28500 | E23: =E66 -> 213750 | F23: =-SUM('UK V4'!O282:W282) -> 133995 | K23: Agency Fees | N23: 209.7
A24: Business rates, service charge, water and elec | B24: =B68 -> 13250.62 | C24: =-'UK V4'!W283 -> 16589 | E24: =E68 -> 114639.98 | F24: =-SUM('UK V4'!O283:W283) -> 128667 | K24: Credits | N24: -375
A25: Opex | B25: =SUM(B46:B64) -> 14408.33 | C25: =-'UK V4'!W286-'UK V4'!W288 -> 12000 | E25: =SUM(E46:E64) -> 93650.69 | F25: =-SUM('UK V4'!O286:W286)-SUM('UK V4'!O288:W288) -> 87782 | K25: Total Sales | N25: =SUM(N21:N24) -> 91894.74
A26: Realised and Unrealised Currency Gains | B26: =B65+B67 -> 101.87 | C26: 0 | E26: =E65+E67 -> 768.6
A27: Total Administrative Costs | B27: =SUM(B22:B26) -> 95805.1 | C27: =SUM(C22:C26) -> 117260.13 | E27: =SUM(E22:E26) -> 625346.17 | F27: =SUM(F22:F26) -> 682806.73
A29: Operating Profit | B29: =B19-B27 -> -13769.1 | C29: =C19-C27 -> 1933.8919 | E29: =E19-E27 -> -193177.17 | F29: =F19-F27 -> -31736.813
A31: Other Income
A32: Discount Received | B32: 0 | C32: 0 | E32: 633.41
A33: Total Other Income | B33: =B32 -> 0 | E33: =E32 -> 633.41
A35: Profit on Ordinary Activities Before Taxation | B35: =(B29 + B33) -> -13769.1 | E35: =(E29 + E33) -> -192543.76
A37: Profit after Taxation | B37: =(B35 - 0) -> -13769.1 | E37: =(E35 - 0) -> -192543.76
A39: Breakdown of Opex from P&L
A40: Administrative Costs
A41: Consulting, Accounting and Administrative Fees | B41: 21305 | E41: 63379.22
A42: Directors' Remuneration | B42: 3775 | E42: 33975
A43: Salaries | B43: 13986.94 | E43: 70175.98
A44: PAYE | B44: 4918.12 | E44: 32847.28
A45: Pension | B45: 309.22 | E45: 2159.42
A46: Advertising & Marketing | B46: 0 | E46: 1000
A47: Bank Fees | B47: 924.51 | E47: 2474.3
A48: Casual Wages | B48: 3107.17 | E48: 30076.57
A49: Cleaning & Office Expenses | B49: 3152.89 | E49: 19169.63
A50: Computer Expenses | B50: 0 | E50: 169.8
A51: Donations | B51: 1000 | E51: 6000
A52: Insurance | B52: 902.25 | E52: 10109.16
... A68: Utilities | B68: 13250.62 | E68: 114639.98
A69: Total Administrative Costs | B69: =SUM(B41:B68) -> 95805.1 | E69: =SUM(E41:E68) -> 625346.17

Sheet UK V4
J1: =YEAR(J3) -> 2024 | K1: =YEAR(K3) -> 2024 | L1: =YEAR(L3) -> 2024 | M1: =YEAR(M3) -> 2025 | N1: =YEAR(N3) -> 2025 | O1: =YEAR(O3) -> 2025 | P1: =YEAR(P3) -> 2025 | Q1: =YEAR(Q3) -> 2025 | ... BH1: =YEAR(BH3) -> 2028
C2: Total Company Cash Flow | D2: =D$331 -> -715914.82 | E2: =E$331 -> -1271416.8 | F2: =F$331 -> 417810.76 | G2: =G$331 -> 1711821.7 | H2: =H$331 -> 2670817.4 | J2: Actual | K2: Actual | L2: Actual | M2: Actuals | N2: Actuals | O2: Actuals | P2: Actuals | Q2: Actuals | R2: Actuals | S2: Actuals | T2: Forecast
C3: GBP | D3: 2024 | E3: =D3+1 -> 2025 | F3: =E3+1 -> 2026 | G3: =F3+1 -> 2027 | H3: =G3+1 -> 2028 | J3: 45596 | K3: =EOMONTH(J3,1) -> 45626 | L3: =EOMONTH(K3,1) -> 45657 | M3: =EOMONTH(L3,1) -> 45688 | N3: =EOMONTH(M3,1) -> 45716 | O3: =EOMONTH(N3,1) -> 45747 | P3: =EOMONTH(O3,1) -> 45777 | Q3: =EOMONTH(P3,1) -> 45808 | R3: =EOMONTH(Q3,1) -> 45838 | ... BH3: =EOMONTH(BG3,1) -> 47118
B4: ASSUMPTIONS
B6: Revenue Assumptions
C8: Treatment commencement | D8: =R3 -> 45838 | J8: =IF(J3>=$D$8,1,0) -> 0 | K8: =IF(K3>=$D$8,1,0) -> 0 | L8: =IF(L3>=$D$8,1,0) -> 0 | M8: =IF(M3>=$D$8,1,0) -> 0 | N8: =IF(N3>=$D$8,1,0) -> 0 | O8: =IF(O3>=$D$8,1,0) -> 0 | P8: =IF(P3>=$D$8,1,0) -> 0 | Q8: =IF(Q3>=$D$8,1,0) -> 0 | ... BH8: =IF(BH3>=$D$8,1,0) -> 1
C11: IV Treatments | D11: Min | E11: Max | F11: Growth Rate
C12: IV Number of Treatments | D12: 30 | E12: 320 | F12: 0.075 | J12: 0 | K12: 0 | L12: 0 | M12: 0 | N12: 0 | O12: 0 | P12: 0 | Q12: 0 | R12: 13 | S12: 16 | T12: =MIN(MAX($D12,S12)*(1+$F12)*T$8,$E12) -> 32.25 | U12: =MIN(MAX($D12,T12)*(1+$F12)*U$8,$E12) -> 34.66875 | V12: =MIN(MAX($D12,U12)*(1+$F12)*V$8,$E12) -> 37.268906 | W12: =MIN(MAX($D12,V12)*(1+$F12)*W$8,$E12) -> 40.064074 | X12: =MIN(MAX($D12,W12)*(1+$F12)*X$8,$E12) -> 43.06888 | Y12: =MIN(MAX($D12,X12)*(1+$F12)*Y$8,$E12) -> 46.299046 | Z12: =MIN(MAX($D12,Y12)*(1+$F12)*Z$8,$E12) -> 49.771474 | AA12: =MIN(MAX($D12,Z12)*(1+$F12)*AA$8,$E12) -> 53.504335 | ... BH12: =MIN(MAX($D12,BG12)*(1+$F12)*BH$8,$E12) -> 320
C13: Average Revenue / Treatment | D13: 450 | E13: 500 | F13: 0.02 | J13: =MIN(MAX($D13,I13)*(1+$F13)*J$8,$E13) -> 0 | K13: =MIN(MAX($D13,J13)*(1+$F13)*K$8,$E13) -> 0 | L13: =MIN(MAX($D13,K13)*(1+$F13)*L$8,$E13) -> 0 | M13: =MIN(MAX($D13,L13)*(1+$F13)*M$8,$E13) -> 0 | N13: =MIN(MAX($D13,M13)*(1+$F13)*N$8,$E13) -> 0 | O13: =MIN(MAX($D13,N13)*(1+$F13)*O$8,$E13) -> 0 | P13: =MIN(MAX($D13,O13)*(1+$F13)*P$8,$E13) -> 0 | Q13: =MIN(MAX($D13,P13)*(1+$F13)*Q$8,$E13) -> 0 | R13: 609 | S13: 474 | T13: =MIN(MAX($D13,S13)*(1+$F13)*T$8,$E13) -> 483.48 | U13: =MIN(MAX($D13,T13)*(1+$F13)*U$8,$E13) -> 493.1496 | V13: =MIN(MAX($D13,U13)*(1+$F13)*V$8,$E13) -> 500 | W13: =MIN(MAX($D13,V13)*(1+$F13)*W$8,$E13) -> 500 | X13: =MIN(MAX($D13,W13)*(1+$F13)*X$8,$E13) -> 500 | Y13: =MIN(MAX($D13,X13)*(1+$F13)*Y$8,$E13) -> 500 | Z13: =MIN(MAX($D13,Y13)*(1+$F13)*Z$8,$E13) -> 500 | AA13: =MIN(MAX($D13,Z13)*(1+$F13)*AA$8,$E13) -> 500 | ... BH13: =MIN(MAX($D13,BG13)*(1+$F13)*BH$8,$E13) -> 500
C14: IV Treatment Revenue | J14: =J12*J13 -> 0 | K14: =K12*K13 -> 0 | L14: =L12*L13 -> 0 | M14: =M12*M13 -> 0 | N14: =N12*N13 -> 0 | O14: =O12*O13 -> 0 | P14: =P12*P13 -> 0 | Q14: =Q12*Q13 -> 0 | ... BH14: =BH12*BH13 -> 160000
C16: IV COS | D16: =-D13*0.3 -> -135 | J16: =-J14*0.4 -> 0 | K16: =-K14*0.4 -> 0 | L16: =-L14*0.4 -> 0 | M16: =-M14*0.4 -> 0 | N16: =-N14*0.4 -> 0 | O16: =-O14*0.4 -> 0 | P16: =-P14*0.4 -> 0 | Q16: =-Q14*0.4 -> 0 | ... S16: =-S14*0.4 -> -3033.6 | T16: =T12*$D16 -> -4353.75 | U16: =U12*$D16 -> -4680.2812 | V16: =V12*$D16 -> -5031.3023 | W16: =W12*$D16 -> -5408.65 | X16: =X12*$D16 -> -5814.2988 | Y16: =Y12*$D16 -> -6250.3712 | Z16: =Z12*$D16 -> -6719.149 | AA16: =AA12*$D16 -> -7223.0852 | ... BH16: =BH12*$D16 -> -43200
C18: IV Curcumin 100mg Treatments | D18: Min | E18: Max | F18: Growth Rate
C19: IV Curcumin 100mg Number of Treatments | D19: 10 | E19: 80 | F19: 0.025 | J19: 0 | K19: 0 | L19: 0 | M19: 0 | N19: 0 | O19: 0 | P19: 0 | Q19: 27 | R19: 22 | S19: 37 | T19: =MIN(MAX($D19,S19)*(1+$F19)*T$8,$E19) -> 37.925 | U19: =MIN(MAX($D19,T19)*(1+$F19)*U$8,$E19) -> 38.873125 | V19: =MIN(MAX($D19,U19)*(1+$F19)*V$8,$E19) -> 39.844953 | W19: =MIN(MAX($D19,V19)*(1+$F19)*W$8,$E19) -> 40.841077 | X19: =MIN(MAX($D19,W19)*(1+$F19)*X$8,$E19) -> 41.862104 | Y19: =MIN(MAX($D19,X19)*(1+$F19)*Y$8,$E19) -> 42.908656 | Z19: =MIN(MAX($D19,Y19)*(1+$F19)*Z$8,$E19) -> 43.981373 | AA19: =MIN(MAX($D19,Z19)*(1+$F19)*AA$8,$E19) -> 45.080907 | ... BH19: =MIN(MAX($D19,BG19)*(1+$F19)*BH$8,$E19) -> 80
C20: Average Revenue / Treatment | D20: 375 | E20: 375 | F20: 0 | J20: =MIN(MAX($D20,I20)*(1+$F20)*J$8,$E20) -> 0 | K20: =MIN(MAX($D20,J20)*(1+$F20)*K$8,$E20) -> 0 | L20: =MIN(MAX($D20,K20)*(1+$F20)*L$8,$E20) -> 0 | M20: =MIN(MAX($D20,L20)*(1+$F20)*M$8,$E20) -> 0 | N20: =MIN(MAX($D20,M20)*(1+$F20)*N$8,$E20) -> 0 | O20: =MIN(MAX($D20,N20)*(1+$F20)*O$8,$E20) -> 0 | P20: =MIN(MAX($D20,O20)*(1+$F20)*P$8,$E20) -> 0 | Q20: 398.55 | R20: 276 | S20: 275 | T20: =MIN(MAX($D20,S20)*(1+$F20)*T$8,$E20) -> 375 | U20: =MIN(MAX($D20,T20)*(1+$F20)*U$8,$E20) -> 375 | V20: =MIN(MAX($D20,U20)*(1+$F20)*V$8,$E20) -> 375 | W20: =MIN(MAX($D20,V20)*(1+$F20)*W$8,$E20) -> 375 | X20: =MIN(MAX($D20,W20)*(1+$F20)*X$8,$E20) -> 375 | Y20: =MIN(MAX($D20,X20)*(1+$F20)*Y$8,$E20) -> 375 | Z20: =MIN(MAX($D20,Y20)*(1+$F20)*Z$8,$E20) -> 375 | AA20: =MIN(MAX($D20,Z20)*(1+$F20)*AA$8,$E20) -> 375 | ... BH20: =MIN(MAX($D20,BG20)*(1+$F20)*BH$8,$E20) -> 375
C21: IV Currcumin 100mg Treatment Revenue | J21: =J19*J20 -> 0 | K21: =K19*K20 -> 0 | L21: =L19*L20 -> 0 | M21: =M19*M20 -> 0 | N21: =N19*N20 -> 0 | O21: =O19*O20 -> 0 | P21: =P19*P20 -> 0 | Q21: =Q19*Q20 -> 10760.85 | ... BH21: =BH19*BH20 -> 30000
C23: IV Curcumin 100mg COS | D23: =-D20*0.3 -> -112.5 | J23: =-J21*0.4 -> 0 | K23: =-K21*0.4 -> 0 | L23: =-L21*0.4 -> 0 | M23: =-M21*0.4 -> 0 | N23: =-N21*0.4 -> 0 | O23: =-O21*0.4 -> 0 | P23: =-P21*0.4 -> 0 | Q23: =-Q21*0.4 -> -4304.34 | ... S23: =-S21*0.4 -> -4070 | T23: =T19*$D23 -> -4266.5625 | U23: =U19*$D23 -> -4373.2266 | V23: =V19*$D23 -> -4482.5572 | W23: =W19*$D23 -> -4594.6212 | X23: =X19*$D23 -> -4709.4867 | Y23: =Y19*$D23 -> -4827.2239 | Z23: =Z19*$D23 -> -4947.9044 | AA23: =AA19*$D23 -> -5071.6021 | ... BH23: =BH19*$D23 -> -9000
C25: Laser Treatments | D25: Min | E25: Max | F25: Growth Rate
C26: Laser Number of Treatments | D26: 17 | E26: 350 | F26: 0.05 | J26: 0 | K26: 0 | L26: 0 | M26: 0 | N26: 0 | O26: 0 | P26: 0 | Q26: 5 | R26: 17 | S26: 19 | T26: =MIN(MAX($D26,S26)*(1+$F26)*T$8,$E26) -> 19.95 | U26: =MIN(MAX($D26,T26)*(1+$F26)*U$8,$E26) -> 20.9475 | V26: =MIN(MAX($D26,U26)*(1+$F26)*V$8,$E26) -> 21.994875 | W26: =MIN(MAX($D26,V26)*(1+$F26)*W$8,$E26) -> 23.094619 | X26: =MIN(MAX($D26,W26)*(1+$F26)*X$8,$E26) -> 24.24935 | Y26: =MIN(MAX($D26,X26)*(1+$F26)*Y$8,$E26) -> 25.461817 | Z26: =MIN(MAX($D26,Y26)*(1+$F26)*Z$8,$E26) -> 26.734908 | AA26: =MIN(MAX($D26,Z26)*(1+$F26)*AA$8,$E26) -> 28.071653 | ... BH26: =MIN(MAX($D26,BG26)*(1+$F26)*BH$8,$E26) -> 140.44777
C27: Average Revenue / Treatment | D27: 100 | E27: 150 | F27: 0 | J27: =MIN(MAX($D27,I27)*(1+$F27)*J$8,$E27) -> 0 | K27: =MIN(MAX($D27,J27)*(1+$F27)*K$8,$E27) -> 0 | L27: =MIN(MAX($D27,K27)*(1+$F27)*L$8,$E27) -> 0 | M27: =MIN(MAX($D27,L27)*(1+$F27)*M$8,$E27) -> 0 | N27: =MIN(MAX($D27,M27)*(1+$F27)*N$8,$E27) -> 0 | O27: =MIN(MAX($D27,N27)*(1+$F27)*O$8,$E27) -> 0 | P27: =MIN(MAX($D27,O27)*(1+$F27)*P$8,$E27) -> 0 | Q27: 84 | R27: 100 | S27: 100 | T27: =MIN(MAX($D27,S27)*(1+$F27)*T$8,$E27) -> 100 | U27: =MIN(MAX($D27,T27)*(1+$F27)*U$8,$E27) -> 100 | V27: =MIN(MAX($D27,U27)*(1+$F27)*V$8,$E27) -> 100 | W27: =MIN(MAX($D27,V27)*(1+$F27)*W$8,$E27) -> 100 | X27: =MIN(MAX($D27,W27)*(1+$F27)*X$8,$E27) -> 100 | Y27: =MIN(MAX($D27,X27)*(1+$F27)*Y$8,$E27) -> 100 | Z27: =MIN(MAX($D27,Y27)*(1+$F27)*Z$8,$E27) -> 100 | AA27: =MIN(MAX($D27,Z27)*(1+$F27)*AA$8,$E27) -> 100 | ... BH27: =MIN(MAX($D27,BG27)*(1+$F27)*BH$8,$E27) -> 100
C28: Laser Patient Revenue | J28: =J26*J27 -> 0 | K28: =K26*K27 -> 0 | L28: =L26*L27 -> 0 | M28: =M26*M27 -> 0 | N28: =N26*N27 -> 0 | O28: =O26*O27 -> 0 | P28: =P26*P27 -> 0 | Q28: =Q26*Q27 -> 420 | ... BH28: =BH26*BH27 -> 14044.777
C30: Hyperthermia (mEHT) 1 | D30: Min | E30: Max | F30: Growth Rate
C31: mEHT Number of Sessions | D31: 60 | E31: 173 | F31: 0.05 | J31: 0 | K31: 0 | L31: 0 | M31: 0 | N31: 0 | O31: 0 | P31: 0 | Q31: 5 | R31: 58 | S31: 62 | T31: 78 | U31: 117 | V31: =MIN(MAX($D31,U31)*(1+$F31)*V$8,$E31) -> 122.85 | W31: =MIN(MAX($D31,V31)*(1+$F31)*W$8,$E31) -> 128.9925 | X31: =MIN(MAX($D31,W31)*(1+$F31)*X$8,$E31) -> 135.44213 | Y31: =MIN(MAX($D31,X31)*(1+$F31)*Y$8,$E31) -> 142.21423 | Z31: =MIN(MAX($D31,Y31)*(1+$F31)*Z$8,$E31) -> 149.32494 | AA31: =MIN(MAX($D31,Z31)*(1+$F31)*AA$8,$E31) -> 156.79119 | AB31: =MIN(MAX($D31,AA31)*(1+$F31)*AB$8,$E31) -> 164.63075 | AC31: =MIN(MAX($D31,AB31)*(1+$F31)*AC$8,$E31) -> 172.86229 | ... BH31: =MIN(MAX($D31,BG31)*(1+$F31)*BH$8,$E31) -> 173
C32: Average Revenue / Session | D32: 300 | E32: 450 | F32: 0 | J32: 0 | K32: 0 | L32: 0 | M32: 0 | N32: 0 | O32: 0 | P32: 0 | Q32: 300 | R32: 292 | S32: 300 | T32: =MIN(MAX($D32,S32)*(1+$F32)*T$8,$E32) -> 300 | U32: =MIN(MAX($D32,T32)*(1+$F32)*U$8,$E32) -> 300 | V32: =MIN(MAX($D32,U32)*(1+$F32)*V$8,$E32) -> 300 | W32: =MIN(MAX($D32,V32)*(1+$F32)*W$8,$E32) -> 300 | X32: =MIN(MAX($D32,W32)*(1+$F32)*X$8,$E32) -> 300 | Y32: =MIN(MAX($D32,X32)*(1+$F32)*Y$8,$E32) -> 300 | Z32: =MIN(MAX($D32,Y32)*(1+$F32)*Z$8,$E32) -> 300 | AA32: =MIN(MAX($D32,Z32)*(1+$F32)*AA$8,$E32) -> 300 | ... BH32: =MIN(MAX($D32,BG32)*(1+$F32)*BH$8,$E32) -> 300
C33: Hyperthermia Session Revenue | J33: =J31*J32 -> 0 | K33: =K31*K32 -> 0 | L33: =L31*L32 -> 0 | M33: =M31*M32 -> 0 | N33: =N31*N32 -> 0 | O33: =O31*O32 -> 0 | P33: =P31*P32 -> 0 | Q33: =Q31*Q32 -> 1500 | ... BH33: =BH31*BH32 -> 51900
C35: Hyperthermia (mEHT) 2
C36: mEHT 2 Treatment commencement | D36: =V3 -> 45961 | J36: =IF(J3=$D$36,1,0) -> 0 | K36: =IF(K3>=$D$36,1,0) -> 0 | L36: =IF(L3>=$D$36,1,0) -> 0 | M36: =IF(M3>=$D$36,1,0) -> 0 | N36: =IF(N3>=$D$36,1,0) -> 0 | O36: =IF(O3>=$D$36,1,0) -> 0 | P36: =IF(P3>=$D$36,1,0) -> 0 | Q36: =IF(Q3>=$D$36,1,0) -> 0 | R36: =IF(R3>=$D$36,1,0) -> 0 | ... BH36: =IF(BH3>=$D$36,1,0) -> 1
D37: Min | E37: Max | F37: Growth Rate
C38: mEHT 2 Number of Sessions | D38: 60 | E38: 173 | F38: 0.05 | J38: 0 | K38: 0 | L38: 0 | M38: 0 | N38: 0 | O38: 0 | P38: 0 | Q38: 0 | R38: 0 | S38: 0 | T38: 0 | U38: 0 | V38: 62 | W38: 78 | X38: 117 | Y38: =MIN(MAX($D38,X38)*(1+$F38)*Y$36,$E38) -> 122.85 | Z38: =MIN(MAX($D38,Y38)*(1+$F38)*Z$36,$E38) -> 128.9925 | AA38: =MIN(MAX($D38,Z38)*(1+$F38)*AA$36,$E38) -> 135.44213 | AB38: =MIN(MAX($D38,AA38)*(1+$F38)*AB$36,$E38) -> 142.21423 | AC38: =MIN(MAX($D38,AB38)*(1+$F38)*AC$36,$E38) -> 149.32494 | AD38: =MIN(MAX($D38,AC38)*(1+$F38)*AD$36,$E38) -> 156.79119 | AE38: =MIN(MAX($D38,AD38)*(1+$F38)*AE$36,$E38) -> 164.63075 | AF38: =MIN(MAX($D38,AE38)*(1+$F38)*AF$36,$E38) -> 172.86229 | ... BH38: =MIN(MAX($D38,BG38)*(1+$F38)*BH$36,$E38) -> 173
C39: Average Revenue / Session | D39: 300 | E39: 450 | F39: 0 | J39: =MIN(MAX($D39,I39)*(1+$F39)*J$36,$E39) -> 0 | K39: =MIN(MAX($D39,J39)*(1+$F39)*K$36,$E39) -> 0 | L39: =MIN(MAX($D39,K39)*(1+$F39)*L$36,$E39) -> 0 | M39: =MIN(MAX($D39,L39)*(1+$F39)*M$36,$E39) -> 0 | N39: =MIN(MAX($D39,M39)*(1+$F39)*N$36,$E39) -> 0 | O39: =MIN(MAX($D39,N39)*(1+$F39)*O$36,$E39) -> 0 | P39: =MIN(MAX($D39,O39)*(1+$F39)*P$36,$E39) -> 0 | Q39: =MIN(MAX($D39,P39)*(1+$F39)*Q$36,$E39) -> 0 | ... BH39: =MIN(MAX($D39,BG39)*(1+$F39)*BH$36,$E39) -> 300
C40: Hyperthermia 2 Session Revenue | J40: =J38*J39 -> 0 | K40: =K38*K39 -> 0 | L40: =L38*L39 -> 0 | M40: =M38*M39 -> 0 | N40: =N38*N39 -> 0 | O40: =O38*O39 -> 0 | P40: =P38*P39 -> 0 | Q40: =Q38*Q39 -> 0 | ... BH40: =BH38*BH39 -> 51900
C42: HBOT 1
C43: HBOT 1 Sessions commencement | D43: =T3 -> 45900 | J43: =IF(J3>=$D$43,1,0) -> 0 | K43: =IF(K3>=$D$43,1,0) -> 0 | L43: =IF(L3>=$D$43,1,0) -> 0 | M43: =IF(M3>=$D$43,1,0) -> 0 | N43: =IF(N3>=$D$43,1,0) -> 0 | O43: =IF(O3>=$D$43,1,0) -> 0 | P43: =IF(P3>=$D$43,1,0) -> 0 | Q43: =IF(Q3>=$D$43,1,0) -> 0 | ... BH43: =IF(BH3>=$D$43,1,0) -> 1
D44: Min | E44: Max | F44: Growth Rate
C45: HBOT 1 Number of Sessions | D45: 20 | E45: 120 | F45: 0.1 | J45: =MIN(MAX($D45,I45)*(1+$F45)*J$43,$E45) -> 0 | K45: =MIN(MAX($D45,J45)*(1+$F45)*K$43,$E45) -> 0 | L45: =MIN(MAX($D45,K45)*(1+$F45)*L$43,$E45) -> 0 | M45: =MIN(MAX($D45,L45)*(1+$F45)*M$43,$E45) -> 0 | N45: =MIN(MAX($D45,M45)*(1+$F45)*N$43,$E45) -> 0 | O45: =MIN(MAX($D45,N45)*(1+$F45)*O$43,$E45) -> 0 | P45: =MIN(MAX($D45,O45)*(1+$F45)*P$43,$E45) -> 0 | Q45: =MIN(MAX($D45,P45)*(1+$F45)*Q$43,$E45) -> 0 | R45: =MIN(MAX($D45,Q45)*(1+$F45)*R$43,$E45) -> 0 | S45: 1 | T45: =MIN(MAX($D45,S45)*(1+$F45)*T$43,$E45) -> 22 | U45: =MIN(MAX($D45,T45)*(1+$F45)*U$43,$E45) -> 24.2 | V45: =MIN(MAX($D45,U45)*(1+$F45)*V$43,$E45) -> 26.62 | W45: =MIN(MAX($D45,V45)*(1+$F45)*W$43,$E45) -> 29.282 | X45: =MIN(MAX($D45,W45)*(1+$F45)*X$43,$E45) -> 32.2102 | Y45: =MIN(MAX($D45,X45)*(1+$F45)*Y$43,$E45) -> 35.43122 | Z45: =MIN(MAX($D45,Y45)*(1+$F45)*Z$43,$E45) -> 38.974342 | AA45: =MIN(MAX($D45,Z45)*(1+$F45)*AA$43,$E45) -> 42.871776 | ... BH45: =MIN(MAX($D45,BG45)*(1+$F45)*BH$43,$E45) -> 120
C46: Average Revenue / Session | D46: 200 | E46: 200 | F46: 0 | J46: =MIN(MAX($D46,I46)*(1+$F46)*J$43,$E46) -> 0 | K46: =MIN(MAX($D46,J46)*(1+$F46)*K$43,$E46) -> 0 | L46: =MIN(MAX($D46,K46)*(1+$F46)*L$43,$E46) -> 0 | M46: =MIN(MAX($D46,L46)*(1+$F46)*M$43,$E46) -> 0 | N46: =MIN(MAX($D46,M46)*(1+$F46)*N$43,$E46) -> 0 | O46: =MIN(MAX($D46,N46)*(1+$F46)*O$43,$E46) -> 0 | P46: =MIN(MAX($D46,O46)*(1+$F46)*P$43,$E46) -> 0 | Q46: =MIN(MAX($D46,P46)*(1+$F46)*Q$43,$E46) -> 0 | R46: =MIN(MAX($D46,Q46)*(1+$F46)*R$43,$E46) -> 0 | S46: 200 | T46: =MIN(MAX($D46,S46)*(1+$F46)*T$43,$E46) -> 200 | U46: =MIN(MAX($D46,T46)*(1+$F46)*U$43,$E46) -> 200 | V46: =MIN(MAX($D46,U46)*(1+$F46)*V$43,$E46) -> 200 | W46: =MIN(MAX($D46,V46)*(1+$F46)*W$43,$E46) -> 200 | X46: =MIN(MAX($D46,W46)*(1+$F46)*X$43,$E46) -> 200 | Y46: =MIN(MAX($D46,X46)*(1+$F46)*Y$43,$E46) -> 200 | Z46: =MIN(MAX($D46,Y46)*(1+$F46)*Z$43,$E46) -> 200 | AA46: =MIN(MAX($D46,Z46)*(1+$F46)*AA$43,$E46) -> 200 | ... BH46: =MIN(MAX($D46,BG46)*(1+$F46)*BH$43,$E46) -> 200
C47: HBOT 1 Session Revenue | J47: =J45*J46 -> 0 | K47: =K45*K46 -> 0 | L47: =L45*L46 -> 0 | M47: =M45*M46 -> 0 | N47: =N45*N46 -> 0 | O47: =O45*O46 -> 0 | P47: =P45*P46 -> 0 | Q47: =Q45*Q46 -> 0 | ... BH47: =BH45*BH46 -> 24000
C49: HBOT 2
C50: HBOT 2 Sessions commencement | D50: 0 | J50: =IF(J3>=$D$50,1,0) -> 1 | K50: =IF(K3>=$D$50,1,0) -> 1 | L50: =IF(L3>=$D$50,1,0) -> 1 | M50: =IF(M3>=$D$50,1,0) -> 1 | N50: =IF(N3>=$D$50,1,0) -> 1 | O50: =IF(O3>=$D$50,1,0) -> 1 | P50: =IF(P3>=$D$50,1,0) -> 1 | Q50: =IF(Q3>=$D$50,1,0) -> 1 | ... BH50: =IF(BH3>=$D$50,1,0) -> 1
D51: Min | E51: Max | F51: Growth Rate
C52: HBOT 2 Number of Sessions | D52: 0 | E52: 0 | F52: 0 | J52: =MIN(MAX($D52,I52)*(1+$F52)*J$50,$E52) -> 0 | K52: =MIN(MAX($D52,J52)*(1+$F52)*K$50,$E52) -> 0 | L52: =MIN(MAX($D52,K52)*(1+$F52)*L$50,$E52) -> 0 | M52: =MIN(MAX($D52,L52)*(1+$F52)*M$50,$E52) -> 0 | N52: =MIN(MAX($D52,M52)*(1+$F52)*N$50,$E52) -> 0 | O52: =MIN(MAX($D52,N52)*(1+$F52)*O$50,$E52) -> 0 | P52: =MIN(MAX($D52,O52)*(1+$F52)*P$50,$E52) -> 0 | Q52: =MIN(MAX($D52,P52)*(1+$F52)*Q$50,$E52) -> 0 | ... BH52: =MIN(MAX($D52,BG52)*(1+$F52)*BH$50,$E52) -> 0
C53: Average Revenue / Session | D53: 0 | E53: 0 | F53: 0 | J53: =MIN(MAX($D53,I53)*(1+$F53)*J$50,$E53) -> 0 | K53: =MIN(MAX($D53,J53)*(1+$F53)*K$50,$E53) -> 0 | L53: =MIN(MAX($D53,K53)*(1+$F53)*L$50,$E53) -> 0 | M53: =MIN(MAX($D53,L53)*(1+$F53)*M$50,$E53) -> 0 | N53: =MIN(MAX($D53,M53)*(1+$F53)*N$50,$E53) -> 0 | O53: =MIN(MAX($D53,N53)*(1+$F53)*O$50,$E53) -> 0 | P53: =MIN(MAX($D53,O53)*(1+$F53)*P$50,$E53) -> 0 | Q53: =MIN(MAX($D53,P53)*(1+$F53)*Q$50,$E53) -> 0 | ... BH53: =MIN(MAX($D53,BG53)*(1+$F53)*BH$50,$E53) -> 0
C54: HBOT 2 Session Revenue | J54: =J52*J53 -> 0 | K54: =K52*K53 -> 0 | L54: =L52*L53 -> 0 | M54: =M52*M53 -> 0 | N54: =N52*N53 -> 0 | O54: =O52*O53 -> 0 | P54: =P52*P53 -> 0 | Q54: =Q52*Q53 -> 0 | ... BH54: =BH52*BH53 -> 0
C56: Photodynamic Therapy (PDT) - CTC
C57: CTC PDT Patients commencement | D57: =W3 -> 45991 | J57: =IF(J3>=$D$57,1,0) -> 0 | K57: =IF(K3>=$D$57,1,0) -> 0 | L57: =IF(L3>=$D$57,1,0) -> 0 | M57: =IF(M3>=$D$57,1,0) -> 0 | N57: =IF(N3>=$D$57,1,0) -> 0 | O57: =IF(O3>=$D$57,1,0) -> 0 | P57: =IF(P3>=$D$57,1,0) -> 0 | Q57: =IF(Q3>=$D$57,1,0) -> 0 | ... BH57: =IF(BH3>=$D$57,1,0) -> 1
D58: Min | E58: Max | F58: Growth Rate
C59: CTC PDT Number of Patients | D59: 1 | E59: 25 | F59: 0.05 | J59: =MIN(MAX($D59,I59)*(1+$F59)*J$57,$E59) -> 0 | K59: =MIN(MAX($D59,J59)*(1+$F59)*K$57,$E59) -> 0 | L59: =MIN(MAX($D59,K59)*(1+$F59)*L$57,$E59) -> 0 | M59: =MIN(MAX($D59,L59)*(1+$F59)*M$57,$E59) -> 0 | N59: =MIN(MAX($D59,M59)*(1+$F59)*N$57,$E59) -> 0 | O59: =MIN(MAX($D59,N59)*(1+$F59)*O$57,$E59) -> 0 | P59: =MIN(MAX($D59,O59)*(1+$F59)*P$57,$E59) -> 0 | Q59: =MIN(MAX($D59,P59)*(1+$F59)*Q$57,$E59) -> 0 | ... BH59: =MIN(MAX($D59,BG59)*(1+$F59)*BH$57,$E59) -> 6.3854773
C60: Average Revenue / Patient / month | D60: 870 | E60: 870 | F60: 0 | J60: =MIN(MAX($D60,I60)*(1+$F60)*J$57,$E60) -> 0 | K60: =MIN(MAX($D60,J60)*(1+$F60)*K$57,$E60) -> 0 | L60: =MIN(MAX($D60,K60)*(1+$F60)*L$57,$E60) -> 0 | M60: =MIN(MAX($D60,L60)*(1+$F60)*M$57,$E60) -> 0 | N60: =MIN(MAX($D60,M60)*(1+$F60)*N$57,$E60) -> 0 | O60: =MIN(MAX($D60,N60)*(1+$F60)*O$57,$E60) -> 0 | P60: =MIN(MAX($D60,O60)*(1+$F60)*P$57,$E60) -> 0 | Q60: =MIN(MAX($D60,P60)*(1+$F60)*Q$57,$E60) -> 0 | ... BH60: =MIN(MAX($D60,BG60)*(1+$F60)*BH$57,$E60) -> 870
C61: CTC PDT Patient Revenue | J61: =J59*J60 -> 0 | K61: =K59*K60 -> 0 | L61: =L59*L60 -> 0 | M61: =M59*M60 -> 0 | N61: =N59*N60 -> 0 | O61: =O59*O60 -> 0 | P61: =P59*P60 -> 0 | Q61: =Q59*Q60 -> 0 | ... BH61: =BH59*BH60 -> 5555.3652
C63: CTC PDT COS | D63: -80 | J63: =J59*$D$63 -> 0 | K63: =K59*$D$63 -> 0 | L63: =L59*$D$63 -> 0 | M63: =M59*$D$63 -> 0 | N63: =N59*$D$63 -> 0 | O63: =O59*$D$63 -> 0 | P63: =P59*$D$63 -> 0 | Q63: =Q59*$D$63 -> 0 | ... BH63: =BH59*$D$63 -> -510.83818
C65: Photodynamic Therapy (PDT)
C66: PDT Patients commencement | D66: =Y3 -> 46053 | J66: =IF(J$3>=$D$66,1,0) -> 0 | K66: =IF(K$3>=$D$66,1,0) -> 0 | L66: =IF(L$3>=$D$66,1,0) -> 0 | M66: =IF(M$3>=$D$66,1,0) -> 0 | N66: =IF(N$3>=$D$66,1,0) -> 0 | O66: =IF(O$3>=$D$66,1,0) -> 0 | P66: =IF(P$3>=$D$66,1,0) -> 0 | Q66: =IF(Q$3>=$D$66,1,0) -> 0 | ... BH66: =IF(BH$3>=$D$66,1,0) -> 1
D67: Min | E67: Max | F67: Growth Rate
C68: PDT Number of Patients | D68: 1 | E68: 1 | F68: 0 | J68: =MIN(MAX($D68,I68)*(1+$F68)*J$66,$E68) -> 0 | K68: =MIN(MAX($D68,J68)*(1+$F68)*K$66,$E68) -> 0 | L68: =MIN(MAX($D68,K68)*(1+$F68)*L$66,$E68) -> 0 | M68: =MIN(MAX($D68,L68)*(1+$F68)*M$66,$E68) -> 0 | N68: =MIN(MAX($D68,M68)*(1+$F68)*N$66,$E68) -> 0 | O68: =MIN(MAX($D68,N68)*(1+$F68)*O$66,$E68) -> 0 | P68: =MIN(MAX($D68,O68)*(1+$F68)*P$66,$E68) -> 0 | Q68: =MIN(MAX($D68,P68)*(1+$F68)*Q$66,$E68) -> 0 | ... BH68: =MIN(MAX($D68,BG68)*(1+$F68)*BH$66,$E68) -> 1
C69: Average Revenue / Patient / month | D69: 2900 | E69: 2900 | F69: 0 | J69: =MIN(MAX($D69,I69)*(1+$F69)*J$66,$E69) -> 0 | K69: =MIN(MAX($D69,J69)*(1+$F69)*K$66,$E69) -> 0 | L69: =MIN(MAX($D69,K69)*(1+$F69)*L$66,$E69) -> 0 | M69: =MIN(MAX($D69,L69)*(1+$F69)*M$66,$E69) -> 0 | N69: =MIN(MAX($D69,M69)*(1+$F69)*N$66,$E69) -> 0 | O69: =MIN(MAX($D69,N69)*(1+$F69)*O$66,$E69) -> 0 | P69: =MIN(MAX($D69,O69)*(1+$F69)*P$66,$E69) -> 0 | Q69: =MIN(MAX($D69,P69)*(1+$F69)*Q$66,$E69) -> 0 | ... BH69: =MIN(MAX($D69,BG69)*(1+$F69)*BH$66,$E69) -> 2900
C70: PDT Patient Revenue | J70: =J68*J69 -> 0 | K70: =K68*K69 -> 0 | L70: =L68*L69 -> 0 | M70: =M68*M69 -> 0 | N70: =N68*N69 -> 0 | O70: =O68*O69 -> 0 | P70: =P68*P69 -> 0 | Q70: =Q68*Q69 -> 0 | ... BH70: =BH68*BH69 -> 2900
C72: PDT COS | D72: -300 | J72: =J68*$D72 -> 0 | K72: =K68*$D72 -> 0 | L72: =L68*$D72 -> 0 | M72: =M68*$D72 -> 0 | N72: =N68*$D72 -> 0 | O72: =O68*$D72 -> 0 | P72: =P68*$D72 -> 0 | Q72: =Q68*$D72 -> 0 | ... BH72: =BH68*$D72 -> -300
C74: VIP Patient
C75: VIP Patients commencement | D75: =D8 -> 45838 | J75: =IF(J3>=$D$75,1,0) -> 0 | K75: =IF(K3>=$D$75,1,0) -> 0 | L75: =IF(L3>=$D$75,1,0) -> 0 | M75: =IF(M3>=$D$75,1,0) -> 0 | N75: =IF(N3>=$D$75,1,0) -> 0 | O75: =IF(O3>=$D$75,1,0) -> 0 | P75: =IF(P3>=$D$75,1,0) -> 0 | Q75: =IF(Q3>=$D$75,1,0) -> 0 | ... BH75: =IF(BH3>=$D$75,1,0) -> 1
D76: Min | E76: Max | F76: Growth Rate
C77: VIP Number of Patients | D77: 1 | E77: 2 | F77: 0.01 | J77: 0 | K77: 0 | L77: 0 | M77: 0 | N77: 0 | O77: 0 | P77: 0 | Q77: 0 | R77: 0.7 | S77: 2.5 | T77: =MIN(MAX($D77,S77)*(1+$F77)*T$75,$E77) -> 2 | U77: =MIN(MAX($D77,T77)*(1+$F77)*U$75,$E77) -> 2 | V77: =MIN(MAX($D77,U77)*(1+$F77)*V$75,$E77) -> 2 | W77: =MIN(MAX($D77,V77)*(1+$F77)*W$75,$E77) -> 2 | X77: =MIN(MAX($D77,W77)*(1+$F77)*X$75,$E77) -> 2 | Y77: =MIN(MAX($D77,X77)*(1+$F77)*Y$75,$E77) -> 2 | Z77: =MIN(MAX($D77,Y77)*(1+$F77)*Z$75,$E77) -> 2 | AA77: =MIN(MAX($D77,Z77)*(1+$F77)*AA$75,$E77) -> 2 | ... BH77: =MIN(MAX($D77,BG77)*(1+$F77)*BH$75,$E77) -> 2
C78: Average Revenue / Patient / month | D78: 5830 | E78: 5830 | F78: 0 | J78: =MIN(MAX($D78,I78)*(1+$F78)*J$75,$E78) -> 0 | K78: =MIN(MAX($D78,J78)*(1+$F78)*K$75,$E78) -> 0 | L78: =MIN(MAX($D78,K78)*(1+$F78)*L$75,$E78) -> 0 | M78: =MIN(MAX($D78,L78)*(1+$F78)*M$75,$E78) -> 0 | N78: =MIN(MAX($D78,M78)*(1+$F78)*N$75,$E78) -> 0 | O78: =MIN(MAX($D78,N78)*(1+$F78)*O$75,$E78) -> 0 | P78: =MIN(MAX($D78,O78)*(1+$F78)*P$75,$E78) -> 0 | Q78: =MIN(MAX($D78,P78)*(1+$F78)*Q$75,$E78) -> 0 | ... BH78: =MIN(MAX($D78,BG78)*(1+$F78)*BH$75,$E78) -> 5830
C79: VIP Patient Revenue | J79: =J77*J78 -> 0 | K79: =K77*K78 -> 0 | L79: =L77*L78 -> 0 | M79: =M77*M78 -> 0 | N79: =N77*N78 -> 0 | O79: =O77*O78 -> 0 | P79: =P77*P78 -> 0 | Q79: =Q77*Q78 -> 0 | ... BH79: =BH77*BH78 -> 11660
C81: VIP COS | D81: =-D78*0.35 -> -2040.5 | J81: =-J79*0.4 -> 0 | K81: =-K79*0.4 -> 0 | L81: =-L79*0.4 -> 0 | M81: =-M79*0.4 -> 0 | N81: =-N79*0.4 -> 0 | O81: =-O79*0.4 -> 0 | P81: =-P79*0.4 -> 0 | Q81: =-Q79*0.4 -> 0 | ... S81: =-S79*0.4 -> -5830 | T81: =T77*$D81 -> -4081 | U81: =U77*$D81 -> -4081 | V81: =V77*$D81 -> -4081 | W81: =W77*$D81 -> -4081 | X81: =X77*$D81 -> -4081 | Y81: =Y77*$D81 -> -4081 | Z81: =Z77*$D81 -> -4081 | AA81: =AA77*$D81 -> -4081 | ... BH81: =BH77*$D81 -> -4081
C83: Sessional Room Rental
C84: Sessional Room Rental commencement | D84: =W3 -> 45991 | J84: =IF(J$3>=$D$84,1,0) -> 0 | K84: =IF(K$3>=$D$84,1,0) -> 0 | L84: =IF(L$3>=$D$84,1,0) -> 0 | M84: =IF(M$3>=$D$84,1,0) -> 0 | N84: =IF(N$3>=$D$84,1,0) -> 0 | O84: =IF(O$3>=$D$84,1,0) -> 0 | P84: =IF(P$3>=$D$84,1,0) -> 0 | Q84: =IF(Q$3>=$D$84,1,0) -> 0 | ... BH84: =IF(BH$3>=$D$84,1,0) -> 1
D86: Min | E86: Max | F86: Growth Rate
C87: Room Rental Number of Sessions | D87: 1 | E87: 200 | F87: 0.1 | I87: 0 | J87: =MIN(MAX($D87,I87)*(1+$F87)*J$84,$E87) -> 0 | K87: =MIN(MAX($D87,J87)*(1+$F87)*K$84,$E87) -> 0 | L87: =MIN(MAX($D87,K87)*(1+$F87)*L$84,$E87) -> 0 | M87: =MIN(MAX($D87,L87)*(1+$F87)*M$84,$E87) -> 0 | N87: =MIN(MAX($D87,M87)*(1+$F87)*N$84,$E87) -> 0 | O87: =MIN(MAX($D87,N87)*(1+$F87)*O$84,$E87) -> 0 | P87: =MIN(MAX($D87,O87)*(1+$F87)*P$84,$E87) -> 0 | Q87: =MIN(MAX($D87,P87)*(1+$F87)*Q$84,$E87) -> 0 | ... BH87: =MIN(MAX($D87,BG87)*(1+$F87)*BH$84,$E87) -> 37.404343
C88: Average Revenue / Session | D88: 60 | E88: 60 | F88: 0 | I88: 0 | J88: =MIN(MAX($D88,I88)*(1+$F88)*J$84,$E88) -> 0 | K88: =MIN(MAX($D88,J88)*(1+$F88)*K$84,$E88) -> 0 | L88: =MIN(MAX($D88,K88)*(1+$F88)*L$84,$E88) -> 0 | M88: =MIN(MAX($D88,L88)*(1+$F88)*M$84,$E88) -> 0 | N88: =MIN(MAX($D88,M88)*(1+$F88)*N$84,$E88) -> 0 | O88: =MIN(MAX($D88,N88)*(1+$F88)*O$84,$E88) -> 0 | P88: =MIN(MAX($D88,O88)*(1+$F88)*P$84,$E88) -> 0 | Q88: =MIN(MAX($D88,P88)*(1+$F88)*Q$84,$E88) -> 0 | ... BH88: =MIN(MAX($D88,BG88)*(1+$F88)*BH$84,$E88) -> 60
C89: Sessional Room Rental Revenue | I89: 0 | J89: =J87*J88 -> 0 | K89: =K87*K88 -> 0 | L89: =L87*L88 -> 0 | M89: =M87*M88 -> 0 | N89: =N87*N88 -> 0 | O89: =O87*O88 -> 0 | P89: =P87*P88 -> 0 | Q89: =Q87*Q88 -> 0 | ... BH89: =BH87*BH88 -> 2244.2606
C91: Consultations | D91: Min | E91: Max | F91: Growth Rate
C92: Consultation Number of Sessions | D92: 10 | E92: 160 | F92: 0.05 | I92: 0 | J92: =MIN(MAX($D92,I92)*(1+$F92)*J$8,$E92) -> 0 | K92: =MIN(MAX($D92,J92)*(1+$F92)*K$8,$E92) -> 0 | L92: =MIN(MAX($D92,K92)*(1+$F92)*L$8,$E92) -> 0 | M92: =MIN(MAX($D92,L92)*(1+$F92)*M$8,$E92) -> 0 | N92: =MIN(MAX($D92,M92)*(1+$F92)*N$8,$E92) -> 0 | O92: =MIN(MAX($D92,N92)*(1+$F92)*O$8,$E92) -> 0 | P92: =MIN(MAX($D92,O92)*(1+$F92)*P$8,$E92) -> 0 | Q92: 12.25 | R92: 12.25 | S92: 14.75 | T92: =MIN(MAX($D92,S92)*(1+$F92)*T$8,$E92) -> 15.4875 | U92: =MIN(MAX($D92,T92)*(1+$F92)*U$8,$E92) -> 16.261875 | V92: =MIN(MAX($D92,U92)*(1+$F92)*V$8,$E92) -> 17.074969 | W92: =MIN(MAX($D92,V92)*(1+$F92)*W$8,$E92) -> 17.928717 | X92: =MIN(MAX($D92,W92)*(1+$F92)*X$8,$E92) -> 18.825153 | Y92: =MIN(MAX($D92,X92)*(1+$F92)*Y$8,$E92) -> 19.766411 | Z92: =MIN(MAX($D92,Y92)*(1+$F92)*Z$8,$E92) -> 20.754731 | AA92: =MIN(MAX($D92,Z92)*(1+$F92)*AA$8,$E92) -> 21.792468 | ... BH92: =MIN(MAX($D92,BG92)*(1+$F92)*BH$8,$E92) -> 109.03183
C93: Average Revenue / Session | D93: 350 | E93: 500 | F93: 0.05 | I93: 0 | J93: =MIN(MAX($D93,I93)*(1+$F93)*J$8,$E93) -> 0 | K93: =MIN(MAX($D93,J93)*(1+$F93)*K$8,$E93) -> 0 | L93: =MIN(MAX($D93,K93)*(1+$F93)*L$8,$E93) -> 0 | M93: =MIN(MAX($D93,L93)*(1+$F93)*M$8,$E93) -> 0 | N93: =MIN(MAX($D93,M93)*(1+$F93)*N$8,$E93) -> 0 | O93: =MIN(MAX($D93,N93)*(1+$F93)*O$8,$E93) -> 0 | P93: =MIN(MAX($D93,O93)*(1+$F93)*P$8,$E93) -> 0 | Q93: 743 | R93: 970 | S93: 722.8 | T93: =MIN(MAX($D93,S93)*(1+$F93)*T$8,$E93) -> 500 | U93: =MIN(MAX($D93,T93)*(1+$F93)*U$8,$E93) -> 500 | V93: =MIN(MAX($D93,U93)*(1+$F93)*V$8,$E93) -> 500 | W93: =MIN(MAX($D93,V93)*(1+$F93)*W$8,$E93) -> 500 | X93: =MIN(MAX($D93,W93)*(1+$F93)*X$8,$E93) -> 500 | Y93: =MIN(MAX($D93,X93)*(1+$F93)*Y$8,$E93) -> 500 | Z93: =MIN(MAX($D93,Y93)*(1+$F93)*Z$8,$E93) -> 500 | AA93: =MIN(MAX($D93,Z93)*(1+$F93)*AA$8,$E93) -> 500 | ... BH93: =MIN(MAX($D93,BG93)*(1+$F93)*BH$8,$E93) -> 500
C94: Consultation Session Revenue | I94: 0 | J94: =J92*J93 -> 0 | K94: =K92*K93 -> 0 | L94: =L92*L93 -> 0 | M94: =M92*M93 -> 0 | N94: =N92*N93 -> 0 | O94: =O92*O93 -> 0 | P94: =P92*P93 -> 0 | Q94: =Q92*Q93 -> 9101.75 | ... BH94: =BH92*BH93 -> 54515.913
I95: 0
C96: Supplements | D96: Min | E96: Max | F96: Growth Rate | I96: 0
C97: Supplements Number of Patients | D97: =D$92*0.75 -> 7.5 | E97: =E$92*0.75 -> 120 | F97: 0.05 | I97: 0 | J97: 0 | K97: 0 | L97: 0 | M97: 0 | N97: 0 | O97: 0 | P97: 0 | Q97: 12 | R97: 7 | S97: 11 | T97: =MIN(MAX($D97,S97)*(1+$F97)*T$8,$E97) -> 11.55 | U97: =MIN(MAX($D97,T97)*(1+$F97)*U$8,$E97) -> 12.1275 | V97: =MIN(MAX($D97,U97)*(1+$F97)*V$8,$E97) -> 12.733875 | W97: =MIN(MAX($D97,V97)*(1+$F97)*W$8,$E97) -> 13.370569 | X97: =MIN(MAX($D97,W97)*(1+$F97)*X$8,$E97) -> 14.039097 | Y97: =MIN(MAX($D97,X97)*(1+$F97)*Y$8,$E97) -> 14.741052 | Z97: =MIN(MAX($D97,Y97)*(1+$F97)*Z$8,$E97) -> 15.478105 | AA97: =MIN(MAX($D97,Z97)*(1+$F97)*AA$8,$E97) -> 16.25201 | ... BH97: =MIN(MAX($D97,BG97)*(1+$F97)*BH$8,$E97) -> 81.31187
C98: Average Revenue / Patient / month | D98: 350 | E98: 500 | F98: 0.05 | I98: 0 | J98: =MIN(MAX($D98,I98)*(1+$F98)*J$8,$E98) -> 0 | K98: =MIN(MAX($D98,J98)*(1+$F98)*K$8,$E98) -> 0 | L98: =MIN(MAX($D98,K98)*(1+$F98)*L$8,$E98) -> 0 | M98: =MIN(MAX($D98,L98)*(1+$F98)*M$8,$E98) -> 0 | N98: =MIN(MAX($D98,M98)*(1+$F98)*N$8,$E98) -> 0 | O98: =MIN(MAX($D98,N98)*(1+$F98)*O$8,$E98) -> 0 | P98: =MIN(MAX($D98,O98)*(1+$F98)*P$8,$E98) -> 0 | Q98: 72 | R98: 88.28 | S98: 65 | T98: =MIN(MAX($D98,S98)*(1+$F98)*T$8,$E98) -> 367.5 | U98: =MIN(MAX($D98,T98)*(1+$F98)*U$8,$E98) -> 385.875 | V98: =MIN(MAX($D98,U98)*(1+$F98)*V$8,$E98) -> 405.16875 | W98: =MIN(MAX($D98,V98)*(1+$F98)*W$8,$E98) -> 425.42719 | X98: =MIN(MAX($D98,W98)*(1+$F98)*X$8,$E98) -> 446.69855 | Y98: =MIN(MAX($D98,X98)*(1+$F98)*Y$8,$E98) -> 469.03347 | Z98: =MIN(MAX($D98,Y98)*(1+$F98)*Z$8,$E98) -> 492.48515 | AA98: =MIN(MAX($D98,Z98)*(1+$F98)*AA$8,$E98) -> 500 | ... BH98: =MIN(MAX($D98,BG98)*(1+$F98)*BH$8,$E98) -> 500
C99: Supplements Patient Revenue | I99: 0 | J99: =J97*J98 -> 0 | K99: =K97*K98 -> 0 | L99: =L97*L98 -> 0 | M99: =M97*M98 -> 0 | N99: =N97*N98 -> 0 | O99: =O97*O98 -> 0 | P99: =P97*P98 -> 0 | Q99: =Q97*Q98 -> 864 | ... BH99: =BH97*BH98 -> 40655.935
I100: 0
C101: Supplement Cost of Sales | D101: =-D98*0.6 -> -210 | J101: =-J99*0.6 -> 0 | K101: =-K99*0.6 -> 0 | L101: =-L99*0.6 -> 0 | M101: =-M99*0.6 -> 0 | N101: =-N99*0.6 -> 0 | O101: =-O99*0.6 -> 0 | P101: =-P99*0.6 -> 0 | Q101: =-Q99*0.6 -> -518.4 | ... S101: =-S99*0.6 -> -429 | T101: =T97*$D101 -> -2425.5 | U101: =U97*$D101 -> -2546.775 | V101: =V97*$D101 -> -2674.1138 | W101: =W97*$D101 -> -2807.8194 | X101: =X97*$D101 -> -2948.2104 | Y101: =Y97*$D101 -> -3095.6209 | Z101: =Z97*$D101 -> -3250.402 | AA101: =AA97*$D101 -> -3412.9221 | ... BH101: =BH97*$D101 -> -17075.493
C103: Oxyhydrogen Therapy
C104: Oxyhydrogen Therapy commencement | D104: =U3 -> 45930 | J104: =IF(J$3>=$D$104,1,0) -> 0 | K104: =IF(K$3>=$D$104,1,0) -> 0 | L104: =IF(L$3>=$D$104,1,0) -> 0 | M104: =IF(M$3>=$D$104,1,0) -> 0 | N104: =IF(N$3>=$D$104,1,0) -> 0 | O104: =IF(O$3>=$D$104,1,0) -> 0 | P104: =IF(P$3>=$D$104,1,0) -> 0 | Q104: =IF(Q$3>=$D$104,1,0) -> 0 | ... BH104: =IF(BH$3>=$D$104,1,0) -> 1
D106: Min | E106: Max | F106: Growth Rate
C107: Oxyhydrogen Therapy Number of Sessions | D107: 20 | E107: 150 | F107: 0.1 | I107: 0 | J107: =MIN(MAX($D107,I107)*(1+$F107)*J$104,$E107) -> 0 | K107: =MIN(MAX($D107,J107)*(1+$F107)*K$104,$E107) -> 0 | L107: =MIN(MAX($D107,K107)*(1+$F107)*L$104,$E107) -> 0 | M107: =MIN(MAX($D107,L107)*(1+$F107)*M$104,$E107) -> 0 | N107: =MIN(MAX($D107,M107)*(1+$F107)*N$104,$E107) -> 0 | O107: =MIN(MAX($D107,N107)*(1+$F107)*O$104,$E107) -> 0 | P107: =MIN(MAX($D107,O107)*(1+$F107)*P$104,$E107) -> 0 | Q107: =MIN(MAX($D107,P107)*(1+$F107)*Q$104,$E107) -> 0 | ... BH107: =MIN(MAX($D107,BG107)*(1+$F107)*BH$104,$E107) -> 150
C108: Average Revenue / Session | D108: 100 | E108: 100 | F108: 0 | I108: 0 | J108: =MIN(MAX($D108,I108)*(1+$F108)*J$104,$E108) -> 0 | K108: =MIN(MAX($D108,J108)*(1+$F108)*K$104,$E108) -> 0 | L108: =MIN(MAX($D108,K108)*(1+$F108)*L$104,$E108) -> 0 | M108: =MIN(MAX($D108,L108)*(1+$F108)*M$104,$E108) -> 0 | N108: =MIN(MAX($D108,M108)*(1+$F108)*N$104,$E108) -> 0 | O108: =MIN(MAX($D108,N108)*(1+$F108)*O$104,$E108) -> 0 | P108: =MIN(MAX($D108,O108)*(1+$F108)*P$104,$E108) -> 0 | Q108: =MIN(MAX($D108,P108)*(1+$F108)*Q$104,$E108) -> 0 | ... BH108: =MIN(MAX($D108,BG108)*(1+$F108)*BH$104,$E108) -> 100
C109: Oxyhydrogen Therapy Revenue | I109: 0 | J109: =J107*J108 -> 0 | K109: =K107*K108 -> 0 | L109: =L107*L108 -> 0 | M109: =M107*M108 -> 0 | N109: =N107*N108 -> 0 | O109: =O107*O108 -> 0 | P109: =P107*P108 -> 0 | Q109: =Q107*Q108 -> 0 | ... BH109: =BH107*BH108 -> 15000
C111: Pathology Services
C112: Pathology Services commencement | D112: =V3 -> 45961 | J112: =IF(J$3>=$D$112,1,0) -> 0 | K112: =IF(K$3>=$D$112,1,0) -> 0 | L112: =IF(L$3>=$D$112,1,0) -> 0 | M112: =IF(M$3>=$D$112,1,0) -> 0 | N112: =IF(N$3>=$D$112,1,0) -> 0 | O112: =IF(O$3>=$D$112,1,0) -> 0 | P112: =IF(P$3>=$D$112,1,0) -> 0 | Q112: =IF(Q$3>=$D$112,1,0) -> 0 | ... BH112: =IF(BH$3>=$D$112,1,0) -> 1
D114: Min | E114: Max | F114: Growth Rate
C115: Pathology Services Number of Sessions | D115: 5 | E115: 50 | F115: 0.1 | I115: 0 | J115: =MIN(MAX($D115,I115)*(1+$F115)*J$112,$E115) -> 0 | K115: =MIN(MAX($D115,J115)*(1+$F115)*K$112,$E115) -> 0 | L115: =MIN(MAX($D115,K115)*(1+$F115)*L$112,$E115) -> 0 | M115: =MIN(MAX($D115,L115)*(1+$F115)*M$112,$E115) -> 0 | N115: =MIN(MAX($D115,M115)*(1+$F115)*N$112,$E115) -> 0 | O115: =MIN(MAX($D115,N115)*(1+$F115)*O$112,$E115) -> 0 | P115: =MIN(MAX($D115,O115)*(1+$F115)*P$112,$E115) -> 0 | Q115: =MIN(MAX($D115,P115)*(1+$F115)*Q$112,$E115) -> 0 | ... BH115: =MIN(MAX($D115,BG115)*(1+$F115)*BH$112,$E115) -> 50
C116: Average Revenue / Session | D116: 100 | E116: 150 | F116: 0 | I116: 0 | J116: =MIN(MAX($D116,I116)*(1+$F116)*J$112,$E116) -> 0 | K116: =MIN(MAX($D116,J116)*(1+$F116)*K$112,$E116) -> 0 | L116: =MIN(MAX($D116,K116)*(1+$F116)*L$112,$E116) -> 0 | M116: =MIN(MAX($D116,L116)*(1+$F116)*M$112,$E116) -> 0 | N116: =MIN(MAX($D116,M116)*(1+$F116)*N$112,$E116) -> 0 | O116: =MIN(MAX($D116,N116)*(1+$F116)*O$112,$E116) -> 0 | P116: =MIN(MAX($D116,O116)*(1+$F116)*P$112,$E116) -> 0 | Q116: =MIN(MAX($D116,P116)*(1+$F116)*Q$112,$E116) -> 0 | ... BH116: =MIN(MAX($D116,BG116)*(1+$F116)*BH$112,$E116) -> 100
C117: Pathology Services Revenue | I117: 0 | J117: =J115*J116 -> 0 | K117: =K115*K116 -> 0 | L117: =L115*L116 -> 0 | M117: =M115*M116 -> 0 | N117: =N115*N116 -> 0 | O117: =O115*O116 -> 0 | P117: =P115*P116 -> 0 | Q117: =Q115*Q116 -> 0 | ... BH117: =BH115*BH116 -> 5000
I118: 0
C119: Sanctura Lite | F119: 4 Months | J119: 0 | K119: 0 | L119: 0 | M119: 12189 | N119: 5857 | O119: 12119 | P119: 5219 | Q119: 0
C120: Oncotherm Bed Sale | D120: 155233.9 | F120: Profit | J120: 0 | K120: 0 | L120: 0 | M120: 0 | N120: 0 | O120: 0 | P120: =$D$120 -> 155233.9 | Q120: 0
I121: 0
C122: =C$12 -> IV Number of Treatments | J122: =J$12 -> 0 | K122: =K$12 -> 0 | L122: =L$12 -> 0 | M122: =M$12 -> 0 | N122: =N$12 -> 0 | O122: =O$12 -> 0 | P122: =P$12 -> 0 | Q122: =Q$12 -> 0 | ... BH122: =BH$12 -> 320
C123: =C$19 -> IV Curcumin 100mg Number of Treatments | J123: =J$19 -> 0 | K123: =K$19 -> 0 | L123: =L$19 -> 0 | M123: =M$19 -> 0 | N123: =N$19 -> 0 | O123: =O$19 -> 0 | P123: =P$19 -> 0 | Q123: =Q$19 -> 27 | ... BH123: =BH$19 -> 80
C124: =C$26 -> Laser Number of Treatments | J124: =J$26 -> 0 | K124: =K$26 -> 0 | L124: =L$26 -> 0 | M124: =M$26 -> 0 | N124: =N$26 -> 0 | O124: =O$26 -> 0 | P124: =P$26 -> 0 | Q124: =Q$26 -> 5 | ... BH124: =BH$26 -> 140.44777
C125: =C$31 -> mEHT Number of Sessions | J125: =J$31 -> 0 | K125: =K$31 -> 0 | L125: =L$31 -> 0 | M125: =M$31 -> 0 | N125: =N$31 -> 0 | O125: =O$31 -> 0 | P125: =P$31 -> 0 | Q125: =Q$31 -> 5 | ... BH125: =BH$31 -> 173
...
